Workbook

Sheet Champions Sheet
A1: Agency | B1: Original Data Collection | C1: Website_Title | D1: Host Name | E1: URL Path | F1: Status | G1: GTM | H1: G-Tag | I1: State of Utah GA Account Y/N | J1: GA property Name | K1: Missing?
A2: BOPP | B2: bop.utah.gov | C2: Board of Pardons & Parole | D2: =IFERROR(__xludf.DUMMYFUNCTION("REGEXEXTRACT(E2, ""^(?:https?:\/\/)?(?:www\.)?([^\/]+)"")"),"bop.utah.gov") -> bop.utah.gov | E2: https://bop.utah.gov | F2: Active (200) | G2: GTM-T34QF72M | H2: G-4VZFST59D0 | I2: Yes | J2: BOPP - Main Website | K2: =IF(H2="", "", IF(ISNUMBER(_xlfn.XMATCH(H2, 'Viks State Rollup Sheet'!G:G)), "Found in Rollup", "MISSING in Rollup")) -> Found in Rollup
A3: CCE | B3: https://artsandmuseums.utah.gov/ | C3: Utah Division of Arts & Museums | A Division of the Department of Cultural & Community Engagement | D3: =IFERROR(__xludf.DUMMYFUNCTION("REGEXEXTRACT(E3, ""^(?:https?:\/\/)?(?:www\.)?([^\/]+)"")"),"artsandmuseums.utah.gov") -> artsandmuseums.utah.gov | E3: https://artsandmuseums.utah.gov/ | F3: Active (200) | G3: None Found | H3: G-76RDJXHW4B | I3: Yes | J3: CCE - AM | K3: =IF(H3="", "", IF(ISNUMBER(_xlfn.XMATCH(H3, 'Viks State Rollup Sheet'!G:G)), "Found in Rollup", "MISSING in Rollup")) -> Found in Rollup
A4: CCE | B4: https://indian.utah.gov/ | C4: Utah Division of Indian Affairs | A Division of the Department of Cultural & Community Engagement | D4: =IFERROR(__xludf.DUMMYFUNCTION("REGEXEXTRACT(E4, ""^(?:https?:\/\/)?(?:www\.)?([^\/]+)"")"),"indian.utah.gov") -> indian.utah.gov | E4: https://indian.utah.gov/ | F4: Active (200) | G4: None Found | H4: G-L41CPHPD25 | I4: Yes | J4: CCE - IA | K4: =IF(H4="", "", IF(ISNUMBER(_xlfn.XMATCH(H4, 'Viks State Rollup Sheet'!G:G)), "Found in Rollup", "MISSING in Rollup")) -> Found in Rollup
A5: CCE | B5: https://multicultural.utah.gov/ | C5: Utah Division Of Multicultural Affairs | A Division of the Utah Department of Cultural and Community Engagement | D5: =IFERROR(__xludf.DUMMYFUNCTION("REGEXEXTRACT(E5, ""^(?:https?:\/\/)?(?:www\.)?([^\/]+)"")"),"multicultural.utah.gov") -> multicultural.utah.gov | E5: https://multicultural.utah.gov/ | F5: Active (200) | G5: None Found | H5: G-BGQYP4L42X | I5: Yes | J5: CCE - MA | K5: =IF(H5="", "", IF(ISNUMBER(_xlfn.XMATCH(H5, 'Viks State Rollup Sheet'!G:G)), "Found in Rollup", "MISSING in Rollup")) -> Found in Rollup
A6: CCE | B6: https://community.utah.gov/ | C6: Home - CCE | D6: =IFERROR(__xludf.DUMMYFUNCTION("REGEXEXTRACT(E6, ""^(?:https?:\/\/)?(?:www\.)?([^\/]+)"")"),"community.utah.gov") -> community.utah.gov | E6: https://community.utah.gov/ | F6: Active (200) | G6: None Found | H6: G-GV5EBLNQCZ | I6: Yes | J6: CCE - Main Website | K6: =IF(H6="", "", IF(ISNUMBER(_xlfn.XMATCH(H6, 'Viks State Rollup Sheet'!G:G)), "Found in Rollup", "MISSING in Rollup")) -> Found in Rollup
A7: CCE | B7: https://community.utah.gov/psuac/ | C7: psuac - CCE | D7: =IFERROR(__xludf.DUMMYFUNCTION("REGEXEXTRACT(E7, ""^(?:https?:\/\/)?(?:www\.)?([^\/]+)"")"),"community.utah.gov") -> community.utah.gov | E7: https://community.utah.gov/psuac/ | F7: Active (200) | G7: None Found | H7: G-GV5EBLNQCZ | I7: Yes | J7: CCE - Main Website | K7: =IF(H7="", "", IF(ISNUMBER(_xlfn.XMATCH(H7, 'Viks State Rollup Sheet'!G:G)), "Found in Rollup", "MISSING in Rollup")) -> Found in Rollup
A8: CCE | B8: https://ushpo.utah.gov/ | C8: Utah State Historic Preservation Office | A Division of the Department of Cultural & Community Engagement | D8: =IFERROR(__xludf.DUMMYFUNCTION("REGEXEXTRACT(E8, ""^(?:https?:\/\/)?(?:www\.)?([^\/]+)"")"),"ushpo.utah.gov") -> ushpo.utah.gov | E8: https://ushpo.utah.gov/ | F8: Active (200) | G8: None Found | H8: G-5SDH2CY979 | I8: Yes | J8: CCE - SHPO | K8: =IF(H8="", "", IF(ISNUMBER(_xlfn.XMATCH(H8, 'Viks State Rollup Sheet'!G:G)), "Found in Rollup", "MISSING in Rollup")) -> Found in Rollup
A9: CCE | B9: https://userve.utah.gov/ | C9: UServeUtah | A Division of the Department of Cultural and Community Engagement | D9: =IFERROR(__xludf.DUMMYFUNCTION("REGEXEXTRACT(E9, ""^(?:https?:\/\/)?(?:www\.)?([^\/]+)"")"),"userve.utah.gov") -> userve.utah.gov | E9: https://userve.utah.gov/ | F9: Active (200) | G9: None Found | H9: G-1RT859T9HN | I9: Yes | J9: CCE - UServeUtah | K9: =IF(H9="", "", IF(ISNUMBER(_xlfn.XMATCH(H9, 'Viks State Rollup Sheet'!G:G)), "Found in Rollup", "MISSING in Rollup")) -> Found in Rollup
A10: CCE | B10: https://library.utah.gov/ | C10: Utah State Library Division | A Division of the Department of Cultural & Community Engagement | D10: =IFERROR(__xludf.DUMMYFUNCTION("REGEXEXTRACT(E10, ""^(?:https?:\/\/)?(?:www\.)?([^\/]+)"")"),"library.utah.gov") -> library.utah.gov | E10: https://library.utah.gov/ | F10: Active (200) | G10: None Found | H10: G-Z519DD5XXQ | I10: Yes | J10: CCE - USL | K10: =IF(H10="", "", IF(ISNUMBER(_xlfn.XMATCH(H10, 'Viks State Rollup Sheet'!G:G)), "Found in Rollup", "MISSING in Rollup")) -> Found in Rollup
A11: CCJJ | B11: https://judicialvacancy.utah.gov/ | C11: Judicial Review - Judicial Vacancy Home | D11: =IFERROR(__xludf.DUMMYFUNCTION("REGEXEXTRACT(E11, ""^(?:https?:\/\/)?(?:www\.)?([^\/]+)"")"),"judicialvacancy.utah.gov") -> judicialvacancy.utah.gov | E11: https://judicialvacancy.utah.gov/ | F11: Active (200) | G11: None Found | H11: G-PCZY0K8JQG, UA-52048446-2 | I11: Yes | J11: CCJJ - Judicial Vacancy | K11: =IF(H11="", "", IF(ISNUMBER(_xlfn.XMATCH(H11, 'Viks State Rollup Sheet'!G:G)), "Found in Rollup", "MISSING in Rollup")) -> MISSING in Rollup
A12: CCJJ | B12: https://justice.utah.gov/ | C12: Department of Criminal Justice | D12: =IFERROR(__xludf.DUMMYFUNCTION("REGEXEXTRACT(E12, ""^(?:https?:\/\/)?(?:www\.)?([^\/]+)"")"),"justice.utah.gov") -> justice.utah.gov | E12: https://justice.utah.gov/ | F12: Active (200) | G12: None Found | H12: G-9SLZ0P2YXT | I12: Yes | J12: CCJJ - Main Website | K12: =IF(H12="", "", IF(ISNUMBER(_xlfn.XMATCH(H12, 'Viks State Rollup Sheet'!G:G)), "Found in Rollup", "MISSING in Rollup")) -> Found in Rollup
A13: CCJJ | B13: https://justice.utah.gov/about-2/ | C13: #N/A | D13: =IFERROR(__xludf.DUMMYFUNCTION("REGEXEXTRACT(E13, ""^(?:https?:\/\/)?(?:www\.)?([^\/]+)"")"),"justice.utah.gov") -> justice.utah.gov | E13: https://justice.utah.gov/about-2/ | F13: Error (404) | G13: HTTP 404 | H13: G-9SLZ0P2YXT | I13: Yes | J13: CCJJ - Main Website | K13: =IF(H13="", "", IF(ISNUMBER(_xlfn.XMATCH(H13, 'Viks State Rollup Sheet'!G:G)), "Found in Rollup", "MISSING in Rollup")) -> Found in Rollup
A14: CCJJ | B14: https://justice.utah.gov/about-ccjj/extraditions/ | C14: Extraditions | Department of Criminal Justice | D14: =IFERROR(__xludf.DUMMYFUNCTION("REGEXEXTRACT(E14, ""^(?:https?:\/\/)?(?:www\.)?([^\/]+)"")"),"justice.utah.gov") -> justice.utah.gov | E14: https://justice.utah.gov/about-ccjj/extraditions/ | F14: Active (200) | G14: None Found | H14: G-9SLZ0P2YXT | I14: Yes | J14: CCJJ - Main Website | K14: =IF(H14="", "", IF(ISNUMBER(_xlfn.XMATCH(H14, 'Viks State Rollup Sheet'!G:G)), "Found in Rollup", "MISSING in Rollup")) -> Found in Rollup
A15: CCJJ | B15: https://justice.utah.gov/about-ccjj/judicial-nominating-commission/ | C15: Judicial Nominating Commission | Department of Criminal Justice | D15: =IFERROR(__xludf.DUMMYFUNCTION("REGEXEXTRACT(E15, ""^(?:https?:\/\/)?(?:www\.)?([^\/]+)"")"),"justice.utah.gov") -> justice.utah.gov | E15: https://justice.utah.gov/about-ccjj/judicial-nominating-commission/ | F15: Active (200) | G15: None Found | H15: G-9SLZ0P2YXT | I15: Yes | J15: CCJJ - Main Website | K15: =IF(H15="", "", IF(ISNUMBER(_xlfn.XMATCH(H15, 'Viks State Rollup Sheet'!G:G)), "Found in Rollup", "MISSING in Rollup")) -> Found in Rollup
A16: CCJJ | B16: https://justice.utah.gov/grants/ | C16: Grants | Department of Criminal Justice | D16: =IFERROR(__xludf.DUMMYFUNCTION("REGEXEXTRACT(E16, ""^(?:https?:\/\/)?(?:www\.)?([^\/]+)"")"),"justice.utah.gov") -> justice.utah.gov | E16: https://justice.utah.gov/grants/ | F16: Active (200) | G16: None Found | H16: G-9SLZ0P2YXT | I16: Yes | J16: CCJJ - Main Website | K16: =IF(H16="", "", IF(ISNUMBER(_xlfn.XMATCH(H16, 'Viks State Rollup Sheet'!G:G)), "Found in Rollup", "MISSING in Rollup")) -> Found in Rollup
A17: CCJJ | B17: https://justice.utah.gov/grants/federal-funding/ | C17: Federal Funding | Department of Criminal Justice | D17: =IFERROR(__xludf.DUMMYFUNCTION("REGEXEXTRACT(E17, ""^(?:https?:\/\/)?(?:www\.)?([^\/]+)"")"),"justice.utah.gov") -> justice.utah.gov | E17: https://justice.utah.gov/grants/federal-funding/ | F17: Active (200) | G17: None Found | H17: G-9SLZ0P2YXT | I17: Yes | J17: CCJJ - Main Website | K17: =IF(H17="", "", IF(ISNUMBER(_xlfn.XMATCH(H17, 'Viks State Rollup Sheet'!G:G)), "Found in Rollup", "MISSING in Rollup")) -> Found in Rollup
A18: CCJJ | B18: https://justice.utah.gov/grants/state-funding/ | C18: State Funding | Department of Criminal Justice | D18: =IFERROR(__xludf.DUMMYFUNCTION("REGEXEXTRACT(E18, ""^(?:https?:\/\/)?(?:www\.)?([^\/]+)"")"),"justice.utah.gov") -> justice.utah.gov | E18: https://justice.utah.gov/grants/state-funding/ | F18: Active (200) | G18: None Found | H18: G-9SLZ0P2YXT | I18: Yes | J18: CCJJ - Main Website | K18: =IF(H18="", "", IF(ISNUMBER(_xlfn.XMATCH(H18, 'Viks State Rollup Sheet'!G:G)), "Found in Rollup", "MISSING in Rollup")) -> Found in Rollup
A19: CCJJ | B19: https://justice.utah.gov/juvenile-justice/ | C19: #N/A | D19: =IFERROR(__xludf.DUMMYFUNCTION("REGEXEXTRACT(E19, ""^(?:https?:\/\/)?(?:www\.)?([^\/]+)"")"),"justice.utah.gov") -> justice.utah.gov | E19: https://justice.utah.gov/juvenile-justice/ | F19: Error (404) | G19: HTTP 404 | H19: G-9SLZ0P2YXT | I19: Yes | J19: CCJJ - Main Website | K19: =IF(H19="", "", IF(ISNUMBER(_xlfn.XMATCH(H19, 'Viks State Rollup Sheet'!G:G)), "Found in Rollup", "MISSING in Rollup")) -> Found in Rollup
A20: CCJJ | B20: https://justice.utah.gov/research-and-reports/ | C20: #N/A | D20: =IFERROR(__xludf.DUMMYFUNCTION("REGEXEXTRACT(E20, ""^(?:https?:\/\/)?(?:www\.)?([^\/]+)"")"),"justice.utah.gov") -> justice.utah.gov | E20: https://justice.utah.gov/research-and-reports/ | F20: Error (404) | G20: HTTP 404 | H20: G-9SLZ0P2YXT | I20: Yes | J20: CCJJ - Main Website | K20: =IF(H20="", "", IF(ISNUMBER(_xlfn.XMATCH(H20, 'Viks State Rollup Sheet'!G:G)), "Found in Rollup", "MISSING in Rollup")) -> Found in Rollup
A21: CCJJ | B21: https://justice.utah.gov/sentencing/ | C21: #N/A | D21: =IFERROR(__xludf.DUMMYFUNCTION("REGEXEXTRACT(E21, ""^(?:https?:\/\/)?(?:www\.)?([^\/]+)"")"),"justice.utah.gov") -> justice.utah.gov | E21: https://justice.utah.gov/sentencing/ | F21: Error (404) | G21: HTTP 404 | H21: G-9SLZ0P2YXT | I21: Yes | J21: CCJJ - Main Website | K21: =IF(H21="", "", IF(ISNUMBER(_xlfn.XMATCH(H21, 'Viks State Rollup Sheet'!G:G)), "Found in Rollup", "MISSING in Rollup")) -> Found in Rollup
A22: CCJJ | B22: https://justice.utah.gov/sentencing/eforms/ | C22: eForms | Department of Criminal Justice | D22: =IFERROR(__xludf.DUMMYFUNCTION("REGEXEXTRACT(E22, ""^(?:https?:\/\/)?(?:www\.)?([^\/]+)"")"),"justice.utah.gov") -> justice.utah.gov | E22: https://justice.utah.gov/sentencing/eforms/ | F22: Active (200) | G22: None Found | H22: G-9SLZ0P2YXT | I22: Yes | J22: CCJJ - Main Website | K22: =IF(H22="", "", IF(ISNUMBER(_xlfn.XMATCH(H22, 'Viks State Rollup Sheet'!G:G)), "Found in Rollup", "MISSING in Rollup")) -> Found in Rollup
A23: CCJJ | B23: https://justice.utah.gov/sentencing/sentencing-and-release-guidelines/ | C23: #N/A | D23: =IFERROR(__xludf.DUMMYFUNCTION("REGEXEXTRACT(E23, ""^(?:https?:\/\/)?(?:www\.)?([^\/]+)"")"),"justice.utah.gov") -> justice.utah.gov | E23: https://justice.utah.gov/sentencing/sentencing-and-release-guidelines/ | F23: Error (404) | G23: HTTP 404 | H23: G-9SLZ0P2YXT | I23: Yes | J23: CCJJ - Main Website | K23: =IF(H23="", "", IF(ISNUMBER(_xlfn.XMATCH(H23, 'Viks State Rollup Sheet'!G:G)), "Found in Rollup", "MISSING in Rollup")) -> Found in Rollup
A24: CCJJ | B24: https://crimevictim.utah.gov/grants/grant-solicitations/ | C24: #N/A | D24: =IFERROR(__xludf.DUMMYFUNCTION("REGEXEXTRACT(E24, ""^(?:https?:\/\/)?(?:www\.)?([^\/]+)"")"),"crimevictim.utah.gov") -> crimevictim.utah.gov | E24: https://crimevictim.utah.gov/grants/grant-solicitations/ | F24: Error (404) | G24: HTTP 404 | H24: G-2NQRP84TH7 | I24: Yes | J24: CCJJ - UOVC | K24: =IF(H24="", "", IF(ISNUMBER(_xlfn.XMATCH(H24, 'Viks State Rollup Sheet'!G:G)), "Found in Rollup", "MISSING in Rollup")) -> Found in Rollup
A25: CCJJ | B25: https://crimevictim.utah.gov/victim-financial-assistance/application-process/ | C25: #N/A | D25: =IFERROR(__xludf.DUMMYFUNCTION("REGEXEXTRACT(E25, ""^(?:https?:\/\/)?(?:www\.)?([^\/]+)"")"),"crimevictim.utah.gov") -> crimevictim.utah.gov | E25: https://crimevictim.utah.gov/victim-financial-assistance/application-process/ | F25: Error (404) | G25: HTTP 404 | H25: G-2NQRP84TH7 | I25: Yes | J25: CCJJ - UOVC | K25: =IF(H25="", "", IF(ISNUMBER(_xlfn.XMATCH(H25, 'Viks State Rollup Sheet'!G:G)), "Found in Rollup", "MISSING in Rollup")) -> Found in Rollup
A26: CCJJ | B26: https://crimevictim.utah.gov/victim-rights/ | C26: #N/A | D26: =IFERROR(__xludf.DUMMYFUNCTION("REGEXEXTRACT(E26, ""^(?:https?:\/\/)?(?:www\.)?([^\/]+)"")"),"crimevictim.utah.gov") -> crimevictim.utah.gov | E26: https://crimevictim.utah.gov/victim-rights/ | F26: Error (404) | G26: HTTP 404 | H26: G-2NQRP84TH7 | I26: Yes | J26: CCJJ - UOVC | K26: =IF(H26="", "", IF(ISNUMBER(_xlfn.XMATCH(H26, 'Viks State Rollup Sheet'!G:G)), "Found in Rollup", "MISSING in Rollup")) -> Found in Rollup
A27: DABS | B27: abs.utah.gov | C27: Utah DABS - Utah DABS | D27: =IFERROR(__xludf.DUMMYFUNCTION("REGEXEXTRACT(E27, ""^(?:https?:\/\/)?(?:www\.)?([^\/]+)"")"),"abs.utah.gov") -> abs.utah.gov | E27: https://abs.utah.gov | F27: Active (200) | G27: GTM-5DQJR6SM | H27: G-X5QN659TK4 | I27: Yes | J27: DABS - Main Website | K27: =IF(H27="", "", IF(ISNUMBER(_xlfn.XMATCH(H27, 'Viks State Rollup Sheet'!G:G)), "Found in Rollup", "MISSING in Rollup")) -> Found in Rollup
A28: DABS | B28: Licensee Ordering Portal | C28: Licensee Ordering Portal | D28: =IFERROR(__xludf.DUMMYFUNCTION("REGEXEXTRACT(E28, ""^(?:https?:\/\/)?(?:www\.)?([^\/]+)"")"),"abs.utah.gov") -> abs.utah.gov | E28: https://abs.utah.gov/licenses-permits/licensee-orders/ | F28: No Original Link | G28: GTM-5DQJR6SM | H28: G-X5QN659TK4 | I28: Yes | J28: DABS - Main Website | K28: =IF(H28="", "", IF(ISNUMBER(_xlfn.XMATCH(H28, 'Viks State Rollup Sheet'!G:G)), "Found in Rollup", "MISSING in Rollup")) -> Found in Rollup
A29: DABS | B29: Licensing and Permitting System | C29: Licensing and Permitting System | D29: =IFERROR(__xludf.DUMMYFUNCTION("REGEXEXTRACT(E29, ""^(?:https?:\/\/)?(?:www\.)?([^\/]+)"")"),"abs.utah.gov") -> abs.utah.gov | E29: https://abs.utah.gov/licenses-permits/licensing-system/ | F29: No Original Link | G29: GTM-5DQJR6SM | H29: G-X5QN659TK4 | I29: Yes | J29: DABS - Main Website | K29: =IF(H29="", "", IF(ISNUMBER(_xlfn.XMATCH(H29, 'Viks State Rollup Sheet'!G:G)), "Found in Rollup", "MISSING in Rollup")) -> Found in Rollup
A30: DABS | B30: Learning Portal (SABA) | C30: Learning Portal (SABA) | D30: =IFERROR(__xludf.DUMMYFUNCTION("REGEXEXTRACT(E30, ""^(?:https?:\/\/)?(?:www\.)?([^\/]+)"")"),"abs.utah.gov") -> abs.utah.gov | E30: https://abs.utah.gov/licenses-permits/training/ | F30: No Original Link | G30: GTM-5DQJR6SM | H30: G-X5QN659TK4 | I30: Yes | J30: DABS - Main Website | K30: =IF(H30="", "", IF(ISNUMBER(_xlfn.XMATCH(H30, 'Viks State Rollup Sheet'!G:G)), "Found in Rollup", "MISSING in Rollup")) -> Found in Rollup
A31: DABS | B31: Special Ordering Portal | C31: Special Ordering Portal | D31: =IFERROR(__xludf.DUMMYFUNCTION("REGEXEXTRACT(E31, ""^(?:https?:\/\/)?(?:www\.)?([^\/]+)"")"),"abs.utah.gov") -> abs.utah.gov | E31: https://abs.utah.gov/shop-products/special-orders/ | F31: No Original Link | G31: GTM-5DQJR6SM | H31: G-X5QN659TK4 | I31: Yes | J31: DABS - Main Website | K31: =IF(H31="", "", IF(ISNUMBER(_xlfn.XMATCH(H31, 'Viks State Rollup Sheet'!G:G)), "Found in Rollup", "MISSING in Rollup")) -> Found in Rollup
A32: DABS | B32: Vendor Portal | C32: Vendor Portal | D32: =IFERROR(__xludf.DUMMYFUNCTION("REGEXEXTRACT(E32, ""^(?:https?:\/\/)?(?:www\.)?([^\/]+)"")"),"abs.utah.gov") -> abs.utah.gov | E32: https://abs.utah.gov/vendors/vendor-portal/ | F32: No Original Link | G32: GTM-5DQJR6SM | H32: G-X5QN659TK4 | I32: Yes | J32: DABS - Main Website | K32: =IF(H32="", "", IF(ISNUMBER(_xlfn.XMATCH(H32, 'Viks State Rollup Sheet'!G:G)), "Found in Rollup", "MISSING in Rollup")) -> Found in Rollup
A33: DABS | B33: Product Locator | C33: Product Locator | D33: =IFERROR(__xludf.DUMMYFUNCTION("REGEXEXTRACT(E33, ""^(?:https?:\/\/)?(?:www\.)?([^\/]+)"")"),"webapps2.abc.utah.gov") -> webapps2.abc.utah.gov | E33: https://webapps2.abc.utah.gov/ProdApps/ProductLocatorCore | F33: No Original Link | G33: None Found | H33: G-X5QN659TK4 | I33: Yes | J33: DABS - Main Website | K33: =IF(H33="", "", IF(ISNUMBER(_xlfn.XMATCH(H33, 'Viks State Rollup Sheet'!G:G)), "Found in Rollup", "MISSING in Rollup")) -> Found in Rollup
A34: DABS | B34: Rare and High Demand Products Portal | C34: Rare and High Demand Products Portal | D34: =IFERROR(__xludf.DUMMYFUNCTION("REGEXEXTRACT(E34, ""^(?:https?:\/\/)?(?:www\.)?([^\/]+)"")"),"webapps2.abc.utah.gov") -> webapps2.abc.utah.gov | E34: https://webapps2.abc.utah.gov/ProdApps/RareHighDemandProducts | F34: No Original Link | G34: None Found | H34: G-X5QN659TK4 | I34: Yes | J34: DABS - Main Website | K34: =IF(H34="", "", IF(ISNUMBER(_xlfn.XMATCH(H34, 'Viks State Rollup Sheet'!G:G)), "Found in Rollup", "MISSING in Rollup")) -> Found in Rollup
A35: DEQ | B35: Large Animal Feeding Operations | C35: Large Animal Feeding Operations | D35: =IFERROR(__xludf.DUMMYFUNCTION("REGEXEXTRACT(E35, ""^(?:https?:\/\/)?(?:www\.)?([^\/]+)"")"),"ag.utah.gov") -> ag.utah.gov | E35: https://ag.utah.gov/conservation/animal-feeding-operations/ | F35: No Original Link | G35: None Found | H35: G-X8DRQJS2B4 | I35: Yes | J35: DAF - Main Website | K35: =IF(H35="", "", IF(ISNUMBER(_xlfn.XMATCH(H35, 'Viks State Rollup Sheet'!G:G)), "Found in Rollup", "MISSING in Rollup")) -> Found in Rollup
A36: UDAF | B36: https://ag.utah.gov/industrialhempprogram/ | C36: Industrial Hemp | Utah Department of Agriculture and Food | D36: =IFERROR(__xludf.DUMMYFUNCTION("REGEXEXTRACT(E36, ""^(?:https?:\/\/)?(?:www\.)?([^\/]+)"")"),"ag.utah.gov") -> ag.utah.gov | E36: https://ag.utah.gov/industrialhempprogram/ | F36: Active (200) | G36: None Found | H36: G-X8DRQJS2B4 | I36: Yes | J36: DAF - Main Website | K36: =IF(H36="", "", IF(ISNUMBER(_xlfn.XMATCH(H36, 'Viks State Rollup Sheet'!G:G)), "Found in Rollup", "MISSING in Rollup")) -> Found in Rollup
A37: UDAF | B37: urrt.utah.gov | C37: Utah Rapid Response Team | D37: =IFERROR(__xludf.DUMMYFUNCTION("REGEXEXTRACT(E37, ""^(?:https?:\/\/)?(?:www\.)?([^\/]+)"")"),"urrt.utah.gov") -> urrt.utah.gov | E37: https://urrt.utah.gov | F37: Active (200) | G37: None Found | H37: G-9B2BJX00ML | I37: Yes | J37: DAF - Rapid Response Team | K37: =IF(H37="", "", IF(ISNUMBER(_xlfn.XMATCH(H37, 'Viks State Rollup Sheet'!G:G)), "Found in Rollup", "MISSING in Rollup")) -> Found in Rollup
A38: DEQ | B38: daqpermitting.utah.gov | C38: Air Quality Permitting Notices - Utah Department of Environmental Quality | D38: =IFERROR(__xludf.DUMMYFUNCTION("REGEXEXTRACT(E38, ""^(?:https?:\/\/)?(?:www\.)?([^\/]+)"")"),"daqpermitting.utah.gov") -> daqpermitting.utah.gov | E38: https://daqpermitting.utah.gov | F38: Active (200) | G38: GTM-54M499X | H38: G-0HM105CNL9 | I38: Yes | J38: DEQ - DAQ - Permitting App | K38: =IF(H38="", "", IF(ISNUMBER(_xlfn.XMATCH(H38, 'Viks State Rollup Sheet'!G:G)), "Found in Rollup", "MISSING in Rollup")) -> Found in Rollup
A39: DEQ | B39: deq.utah.gov | C39: Home - Utah Department of Environmental Quality | D39: =IFERROR(__xludf.DUMMYFUNCTION("REGEXEXTRACT(E39, ""^(?:https?:\/\/)?(?:www\.)?([^\/]+)"")"),"deq.utah.gov") -> deq.utah.gov | E39: https://deq.utah.gov | F39: Active (200) | G39: GTM-P5KCN7V | H39: G-RRTEGT2P5N | I39: Yes | J39: DEQ - Main Website | K39: =IF(H39="", "", IF(ISNUMBER(_xlfn.XMATCH(H39, 'Viks State Rollup Sheet'!G:G)), "Found in Rollup", "MISSING in Rollup")) -> Found in Rollup
A40: DEQ | B40: Air Quality Complaint Form | C40: Air Quality Complaint Form | D40: =IFERROR(__xludf.DUMMYFUNCTION("REGEXEXTRACT(E40, ""^(?:https?:\/\/)?(?:www\.)?([^\/]+)"")"),"deq.utah.gov") -> deq.utah.gov | E40: https://deq.utah.gov/daq/air-quality-complaint-form | F40: No Original Link | G40: GTM-P5KCN7V | H40: G-RRTEGT2P5N | I40: Yes | J40: DEQ - Main Website | K40: =IF(H40="", "", IF(ISNUMBER(_xlfn.XMATCH(H40, 'Viks State Rollup Sheet'!G:G)), "Found in Rollup", "MISSING in Rollup")) -> Found in Rollup
A41: DEQ | B41: Air Quality Permitting | C41: Air Quality Permitting | D41: =IFERROR(__xludf.DUMMYFUNCTION("REGEXEXTRACT(E41, ""^(?:https?:\/\/)?(?:www\.)?([^\/]+)"")"),"deq.utah.gov") -> deq.utah.gov | E41: https://deq.utah.gov/daq/air-quality-permitting | F41: No Original Link | G41: GTM-P5KCN7V | H41: G-RRTEGT2P5N | I41: Yes | J41: DEQ - Main Website | K41: =IF(H41="", "", IF(ISNUMBER(_xlfn.XMATCH(H41, 'Viks State Rollup Sheet'!G:G)), "Found in Rollup", "MISSING in Rollup")) -> Found in Rollup
A42: DEQ | B42: General Permitting | C42: General Permitting | D42: =IFERROR(__xludf.DUMMYFUNCTION("REGEXEXTRACT(E42, ""^(?:https?:\/\/)?(?:www\.)?([^\/]+)"")"),"deq.utah.gov") -> deq.utah.gov | E42: https://deq.utah.gov/daq/air-quality-permitting-general | F42: No Original Link | G42: GTM-P5KCN7V | H42: G-RRTEGT2P5N | I42: Yes | J42: DEQ - Main Website | K42: =IF(H42="", "", IF(ISNUMBER(_xlfn.XMATCH(H42, 'Viks State Rollup Sheet'!G:G)), "Found in Rollup", "MISSING in Rollup")) -> Found in Rollup
A43: DEQ | B43: Lead and Asbestos certificaiton with local contractors | C43: Lead and Asbestos certificaiton with local contractors | D43: =IFERROR(__xludf.DUMMYFUNCTION("REGEXEXTRACT(E43, ""^(?:https?:\/\/)?(?:www\.)?([^\/]+)"")"),"deq.utah.gov") -> deq.utah.gov | E43: https://deq.utah.gov/daq/asbestos | F43: No Original Link | G43: GTM-P5KCN7V | H43: G-RRTEGT2P5N | I43: Yes | J43: DEQ - Main Website | K43: =IF(H43="", "", IF(ISNUMBER(_xlfn.XMATCH(H43, 'Viks State Rollup Sheet'!G:G)), "Found in Rollup", "MISSING in Rollup")) -> Found in Rollup
A44: DEQ | B44: Air Quality Inventory Point Source | C44: Air Quality Inventory Point Source | D44: =IFERROR(__xludf.DUMMYFUNCTION("REGEXEXTRACT(E44, ""^(?:https?:\/\/)?(?:www\.)?([^\/]+)"")"),"deq.utah.gov") -> deq.utah.gov | E44: https://deq.utah.gov/daq/point-source-emission-inventories | F44: No Original Link | G44: GTM-P5KCN7V | H44: G-RRTEGT2P5N | I44: Yes | J44: DEQ - Main Website | K44: =IF(H44="", "", IF(ISNUMBER(_xlfn.XMATCH(H44, 'Viks State Rollup Sheet'!G:G)), "Found in Rollup", "MISSING in Rollup")) -> Found in Rollup
A45: DEQ | B45: Air Quality Minor Source Compliance | C45: Air Quality Minor Source Compliance | D45: =IFERROR(__xludf.DUMMYFUNCTION("REGEXEXTRACT(E45, ""^(?:https?:\/\/)?(?:www\.)?([^\/]+)"")"),"deq.utah.gov") -> deq.utah.gov | E45: https://deq.utah.gov/daq/source-size-categories | F45: No Original Link | G45: GTM-P5KCN7V | H45: G-RRTEGT2P5N | I45: Yes | J45: DEQ - Main Website | K45: =IF(H45="", "", IF(ISNUMBER(_xlfn.XMATCH(H45, 'Viks State Rollup Sheet'!G:G)), "Found in Rollup", "MISSING in Rollup")) -> Found in Rollup
A46: DEQ | B46: Air Quality Major Source Compliance | C46: Air Quality Major Source Compliance | D46: =IFERROR(__xludf.DUMMYFUNCTION("REGEXEXTRACT(E46, ""^(?:https?:\/\/)?(?:www\.)?([^\/]+)"")"),"deq.utah.gov") -> deq.utah.gov | E46: https://deq.utah.gov/daq/source-size-categories | F46: No Original Link | G46: GTM-P5KCN7V | H46: G-RRTEGT2P5N | I46: Yes | J46: DEQ - Main Website | K46: =IF(H46="", "", IF(ISNUMBER(_xlfn.XMATCH(H46, 'Viks State Rollup Sheet'!G:G)), "Found in Rollup", "MISSING in Rollup")) -> Found in Rollup
A47: DEQ | B47: Backflow Assembly Tester Certification Application | C47: Backflow Assembly Tester Certification Application | D47: =IFERROR(__xludf.DUMMYFUNCTION("REGEXEXTRACT(E47, ""^(?:https?:\/\/)?(?:www\.)?([^\/]+)"")"),"deq.utah.gov") -> deq.utah.gov | E47: https://deq.utah.gov/ddw/backflow-assembly-tester | F47: No Original Link | G47: GTM-P5KCN7V | H47: G-RRTEGT2P5N | I47: Yes | J47: DEQ - Main Website | K47: =IF(H47="", "", IF(ISNUMBER(_xlfn.XMATCH(H47, 'Viks State Rollup Sheet'!G:G)), "Found in Rollup", "MISSING in Rollup")) -> Found in Rollup
A48: DEQ | B48: Renewals: Cross Connection Control Program Administrator | C48: Renewals: Cross Connection Control Program Administrator | D48: =IFERROR(__xludf.DUMMYFUNCTION("REGEXEXTRACT(E48, ""^(?:https?:\/\/)?(?:www\.)?([^\/]+)"")"),"deq.utah.gov") -> deq.utah.gov | E48: https://deq.utah.gov/ddw/ccc-admin | F48: No Original Link | G48: GTM-P5KCN7V | H48: G-RRTEGT2P5N | I48: Yes | J48: DEQ - Main Website | K48: =IF(H48="", "", IF(ISNUMBER(_xlfn.XMATCH(H48, 'Viks State Rollup Sheet'!G:G)), "Found in Rollup", "MISSING in Rollup")) -> Found in Rollup
A49: DEQ | B49: New Certifications: Cross Connection Control Program Administrator | C49: New Certifications: Cross Connection Control Program Administrator | D49: =IFERROR(__xludf.DUMMYFUNCTION("REGEXEXTRACT(E49, ""^(?:https?:\/\/)?(?:www\.)?([^\/]+)"")"),"deq.utah.gov") -> deq.utah.gov | E49: https://deq.utah.gov/ddw/ccc-admin | F49: No Original Link | G49: GTM-P5KCN7V | H49: G-RRTEGT2P5N | I49: Yes | J49: DEQ - Main Website | K49: =IF(H49="", "", IF(ISNUMBER(_xlfn.XMATCH(H49, 'Viks State Rollup Sheet'!G:G)), "Found in Rollup", "MISSING in Rollup")) -> Found in Rollup
A50: DEQ | B50: Operator Hiring Center | C50: Operator Hiring Center | D50: =IFERROR(__xludf.DUMMYFUNCTION("REGEXEXTRACT(E50, ""^(?:https?:\/\/)?(?:www\.)?([^\/]+)"")"),"deq.utah.gov") -> deq.utah.gov | E50: https://deq.utah.gov/ddw/operator-hiring-center | F50: No Original Link | G50: GTM-P5KCN7V | H50: G-RRTEGT2P5N | I50: Yes | J50: DEQ - Main Website | K50: =IF(H50="", "", IF(ISNUMBER(_xlfn.XMATCH(H50, 'Viks State Rollup Sheet'!G:G)), "Found in Rollup", "MISSING in Rollup")) -> Found in Rollup
A51: DEQ | B51: DDW Customer Survey [Sanitary Survey] | C51: DDW Customer Survey [Sanitary Survey] | D51: =IFERROR(__xludf.DUMMYFUNCTION("REGEXEXTRACT(E51, ""^(?:https?:\/\/)?(?:www\.)?([^\/]+)"")"),"deq.utah.gov") -> deq.utah.gov | E51: https://deq.utah.gov/ddw/sanitary-surveys | F51: No Original Link | G51: GTM-P5KCN7V | H51: G-RRTEGT2P5N | I51: Yes | J51: DEQ - Main Website | K51: =IF(H51="", "", IF(ISNUMBER(_xlfn.XMATCH(H51, 'Viks State Rollup Sheet'!G:G)), "Found in Rollup", "MISSING in Rollup")) -> Found in Rollup
A52: DEQ | B52: Air Quality Oil & Gas Compliance | C52: Air Quality Oil & Gas Compliance | D52: =IFERROR(__xludf.DUMMYFUNCTION("REGEXEXTRACT(E52, ""^(?:https?:\/\/)?(?:www\.)?([^\/]+)"")"),"deq.utah.gov") -> deq.utah.gov | E52: https://deq.utah.gov/derr/derr-compliance | F52: No Original Link | G52: GTM-P5KCN7V | H52: G-RRTEGT2P5N | I52: Yes | J52: DEQ - Main Website | K52: =IF(H52="", "", IF(ISNUMBER(_xlfn.XMATCH(H52, 'Viks State Rollup Sheet'!G:G)), "Found in Rollup", "MISSING in Rollup")) -> Found in Rollup
A53: DEQ | B53: Petroleum Storage Tanks | C53: Petroleum Storage Tanks | D53: =IFERROR(__xludf.DUMMYFUNCTION("REGEXEXTRACT(E53, ""^(?:https?:\/\/)?(?:www\.)?([^\/]+)"")"),"deq.utah.gov") -> deq.utah.gov | E53: https://deq.utah.gov/derr/pst | F53: No Original Link | G53: GTM-P5KCN7V | H53: G-RRTEGT2P5N | I53: Yes | J53: DEQ - Main Website | K53: =IF(H53="", "", IF(ISNUMBER(_xlfn.XMATCH(H53, 'Viks State Rollup Sheet'!G:G)), "Found in Rollup", "MISSING in Rollup")) -> Found in Rollup
A54: DEQ | B54: Groundwater Protection | C54: Groundwater Protection | D54: =IFERROR(__xludf.DUMMYFUNCTION("REGEXEXTRACT(E54, ""^(?:https?:\/\/)?(?:www\.)?([^\/]+)"")"),"deq.utah.gov") -> deq.utah.gov | E54: https://deq.utah.gov/dwq/ground-water-permits | F54: No Original Link | G54: GTM-P5KCN7V | H54: G-RRTEGT2P5N | I54: Yes | J54: DEQ - Main Website | K54: =IF(H54="", "", IF(ISNUMBER(_xlfn.XMATCH(H54, 'Viks State Rollup Sheet'!G:G)), "Found in Rollup", "MISSING in Rollup")) -> Found in Rollup
A55: DEQ | B55: UPDES Compliance Assistance | C55: UPDES Compliance Assistance | D55: =IFERROR(__xludf.DUMMYFUNCTION("REGEXEXTRACT(E55, ""^(?:https?:\/\/)?(?:www\.)?([^\/]+)"")"),"deq.utah.gov") -> deq.utah.gov | E55: https://deq.utah.gov/dwq/uic-assistance | F55: No Original Link | G55: GTM-P5KCN7V | H55: G-RRTEGT2P5N | I55: Yes | J55: DEQ - Main Website | K55: =IF(H55="", "", IF(ISNUMBER(_xlfn.XMATCH(H55, 'Viks State Rollup Sheet'!G:G)), "Found in Rollup", "MISSING in Rollup")) -> Found in Rollup
A56: DEQ | B56: Individual Permitting | C56: Individual Permitting | D56: =IFERROR(__xludf.DUMMYFUNCTION("REGEXEXTRACT(E56, ""^(?:https?:\/\/)?(?:www\.)?([^\/]+)"")"),"deq.utah.gov") -> deq.utah.gov | E56: https://deq.utah.gov/dwq/water-quality-permitting | F56: No Original Link | G56: GTM-P5KCN7V | H56: G-RRTEGT2P5N | I56: Yes | J56: DEQ - Main Website | K56: =IF(H56="", "", IF(ISNUMBER(_xlfn.XMATCH(H56, 'Viks State Rollup Sheet'!G:G)), "Found in Rollup", "MISSING in Rollup")) -> Found in Rollup
A57: DEQ | B57: Wastewater Certification | C57: Wastewater Certification | D57: =IFERROR(__xludf.DUMMYFUNCTION("REGEXEXTRACT(E57, ""^(?:https?:\/\/)?(?:www\.)?([^\/]+)"")"),"deq.utah.gov") -> deq.utah.gov | E57: https://deq.utah.gov/dwq/ww-opcert | F57: No Original Link | G57: GTM-P5KCN7V | H57: G-RRTEGT2P5N | I57: Yes | J57: DEQ - Main Website | K57: =IF(H57="", "", IF(ISNUMBER(_xlfn.XMATCH(H57, 'Viks State Rollup Sheet'!G:G)), "Found in Rollup", "MISSING in Rollup")) -> Found in Rollup
A58: DFI | B58: https://dfi.utah.gov/ | C58: Utah Department of Financial Institutions | D58: =IFERROR(__xludf.DUMMYFUNCTION("REGEXEXTRACT(E58, ""^(?:https?:\/\/)?(?:www\.)?([^\/]+)"")"),"dfi.utah.gov") -> dfi.utah.gov | E58: https://dfi.utah.gov/ | F58: Active (200) | G58: None Found | H58: G-5QSCPJ8N22 | I58: Yes | J58: DFI - Main website | K58: =IF(H58="", "", IF(ISNUMBER(_xlfn.XMATCH(H58, 'Viks State Rollup Sheet'!G:G)), "Found in Rollup", "MISSING in Rollup")) -> Found in Rollup
A59: DGO | B59: archives.utah.gov | C59: Utah Division of Archives and Records Service | D59: =IFERROR(__xludf.DUMMYFUNCTION("REGEXEXTRACT(E59, ""^(?:https?:\/\/)?(?:www\.)?([^\/]+)"")"),"archives.utah.gov") -> archives.utah.gov | E59: https://archives.utah.gov | F59: Active (200) | G59: GTM-MSNV2MMM | H59: G-LCDV67YMH0, G-YGCRKVWVNN | I59: Yes | J59: DGO - DARS Archives | K59: =IF(H59="", "", IF(ISNUMBER(_xlfn.XMATCH(H59, 'Viks State Rollup Sheet'!G:G)), "Found in Rollup", "MISSING in Rollup")) -> MISSING in Rollup
A60: DGO | B60: dfcm.utah.gov | C60: Division of Facilities Construction & Management | D60: =IFERROR(__xludf.DUMMYFUNCTION("REGEXEXTRACT(E60, ""^(?:https?:\/\/)?(?:www\.)?([^\/]+)"")"),"dfcm.utah.gov") -> dfcm.utah.gov | E60: https://dfcm.utah.gov | F60: Active (200) | G60: GTM-TMKQPNQT | H60: G-LCDV67YMH0, G-X7JN19E1P8 | I60: Yes | J60: DGO - DFCM | K60: =IF(H60="", "", IF(ISNUMBER(_xlfn.XMATCH(H60, 'Viks State Rollup Sheet'!G:G)), "Found in Rollup", "MISSING in Rollup")) -> MISSING in Rollup
A61: DGO | B61: fleet.utah.gov | C61: Division of Fleet Operations | Division of Fleet Operations | D61: =IFERROR(__xludf.DUMMYFUNCTION("REGEXEXTRACT(E61, ""^(?:https?:\/\/)?(?:www\.)?([^\/]+)"")"),"fleet.utah.gov") -> fleet.utah.gov | E61: https://fleet.utah.gov | F61: Active (200) | G61: GTM-W4Z3JVWF | H61: G-HL2ZC77NLB, G-LCDV67YMH0 | I61: Yes | J61: DGO - DFO | K61: =IF(H61="", "", IF(ISNUMBER(_xlfn.XMATCH(H61, 'Viks State Rollup Sheet'!G:G)), "Found in Rollup", "MISSING in Rollup")) -> MISSING in Rollup
A62: DGO | B62: dhrm.utah.gov | C62: Division of Human Resource Management | Working together for a better Utah | D62: =IFERROR(__xludf.DUMMYFUNCTION("REGEXEXTRACT(E62, ""^(?:https?:\/\/)?(?:www\.)?([^\/]+)"")"),"dhrm.utah.gov") -> dhrm.utah.gov | E62: https://dhrm.utah.gov | F62: Active (200) | G62: GTM-W546X56X | H62: G-DQLJWFSR8W, G-LCDV67YMH0 | I62: Yes | J62: DGO - DHRM | K62: =IF(H62="", "", IF(ISNUMBER(_xlfn.XMATCH(H62, 'Viks State Rollup Sheet'!G:G)), "Found in Rollup", "MISSING in Rollup")) -> MISSING in Rollup
A63: DGO | B63: jobdesc.utah.gov | C63: Job Description Search | D63: =IFERROR(__xludf.DUMMYFUNCTION("REGEXEXTRACT(E63, ""^(?:https?:\/\/)?(?:www\.)?([^\/]+)"")"),"jobdesc.utah.gov") -> jobdesc.utah.gov | E63: https://jobdesc.utah.gov | F63: Active (200) | G63: None Found | H63: G-N4CB7E1M9C | I63: Yes | J63: DGO - DHRM - Job Description Search | K63: =IF(H63="", "", IF(ISNUMBER(_xlfn.XMATCH(H63, 'Viks State Rollup Sheet'!G:G)), "Found in Rollup", "MISSING in Rollup")) -> Found in Rollup
A64: DGO | B64: purchasing.utah.gov | C64: Division of Purchasing and General Services | D64: =IFERROR(__xludf.DUMMYFUNCTION("REGEXEXTRACT(E64, ""^(?:https?:\/\/)?(?:www\.)?([^\/]+)"")"),"purchasing.utah.gov") -> purchasing.utah.gov | E64: https://purchasing.utah.gov | F64: Active (200) | G64: GTM-PHGWTJVS | H64: G-GQ4MYHDMV7, G-LCDV67YMH0 | I64: Yes | J64: DGO - DPGS | K64: =IF(H64="", "", IF(ISNUMBER(_xlfn.XMATCH(H64, 'Viks State Rollup Sheet'!G:G)), "Found in Rollup", "MISSING in Rollup")) -> MISSING in Rollup
A65: DGO | B65: risk.utah.gov | C65: Division of Risk Management | D65: =IFERROR(__xludf.DUMMYFUNCTION("REGEXEXTRACT(E65, ""^(?:https?:\/\/)?(?:www\.)?([^\/]+)"")"),"risk.utah.gov") -> risk.utah.gov | E65: https://risk.utah.gov | F65: Active (200) | G65: GTM-WRJ32XTD | H65: G-LCDV67YMH0, G-QP2SHHKWVK | I65: Yes | J65: DGO - DRM | K65: =IF(H65="", "", IF(ISNUMBER(_xlfn.XMATCH(H65, 'Viks State Rollup Sheet'!G:G)), "Found in Rollup", "MISSING in Rollup")) -> MISSING in Rollup
A66: DGO | B66: dts.utah.gov | C66: Division of Technology Services | D66: =IFERROR(__xludf.DUMMYFUNCTION("REGEXEXTRACT(E66, ""^(?:https?:\/\/)?(?:www\.)?([^\/]+)"")"),"dts.utah.gov") -> dts.utah.gov | E66: https://dts.utah.gov | F66: Active (200) | G66: GTM-PBK2TXFX | H66: G-J5CFQ0YBXN, G-LCDV67YMH0 | I66: Yes | J66: DGO - DTS | K66: =IF(H66="", "", IF(ISNUMBER(_xlfn.XMATCH(H66, 'Viks State Rollup Sheet'!G:G)), "Found in Rollup", "MISSING in Rollup")) -> MISSING in Rollup
A67: DGO | B67: finance.utah.gov | C67: Division of Finance | D67: =IFERROR(__xludf.DUMMYFUNCTION("REGEXEXTRACT(E67, ""^(?:https?:\/\/)?(?:www\.)?([^\/]+)"")"),"finance.utah.gov") -> finance.utah.gov | E67: https://finance.utah.gov | F67: Active (200) | G67: GTM-TVHM3BCV | H67: G-6WSH2Z0GH2, G-LCDV67YMH0 | I67: Yes | J67: DGO - Finance | K67: =IF(H67="", "", IF(ISNUMBER(_xlfn.XMATCH(H67, 'Viks State Rollup Sheet'!G:G)), "Found in Rollup", "MISSING in Rollup")) -> MISSING in Rollup
A68: DGO | B68: SAP Concur | C68: SAP Concur | D68: =IFERROR(__xludf.DUMMYFUNCTION("REGEXEXTRACT(E68, ""^(?:https?:\/\/)?(?:www\.)?([^\/]+)"")"),"finance.utah.gov") -> finance.utah.gov | E68: https://finance.utah.gov/travel-and-p-card/log-into-concur/ | F68: No Original Link | G68: GTM-TVHM3BCV | H68: G-6WSH2Z0GH2, G-LCDV67YMH0 | I68: Yes | J68: DGO - Finance | K68: =IF(H68="", "", IF(ISNUMBER(_xlfn.XMATCH(H68, 'Viks State Rollup Sheet'!G:G)), "Found in Rollup", "MISSING in Rollup")) -> MISSING in Rollup
A69: DGO | B69: govops.utah.gov | C69: Department of Government Operations | D69: =IFERROR(__xludf.DUMMYFUNCTION("REGEXEXTRACT(E69, ""^(?:https?:\/\/)?(?:www\.)?([^\/]+)"")"),"govops.utah.gov") -> govops.utah.gov | E69: https://govops.utah.gov | F69: Active (200) | G69: GTM-TWRVDPGX | H69: G-G8NLKD6M0E, G-LCDV67YMH0 | I69: Yes | J69: DGO - Main Website | K69: =IF(H69="", "", IF(ISNUMBER(_xlfn.XMATCH(H69, 'Viks State Rollup Sheet'!G:G)), "Found in Rollup", "MISSING in Rollup")) -> MISSING in Rollup
A70: DGO | B70: rules.utah.gov | C70: Office of Administrative Rules | D70: =IFERROR(__xludf.DUMMYFUNCTION("REGEXEXTRACT(E70, ""^(?:https?:\/\/)?(?:www\.)?([^\/]+)"")"),"rules.utah.gov") -> rules.utah.gov | E70: https://rules.utah.gov | F70: Active (200) | G70: GTM-PWKDN9QN | H70: G-LCDV67YMH0, G-TQH1CNGHRR | I70: Yes | J70: DGO - OAR | K70: =IF(H70="", "", IF(ISNUMBER(_xlfn.XMATCH(H70, 'Viks State Rollup Sheet'!G:G)), "Found in Rollup", "MISSING in Rollup")) -> MISSING in Rollup
A71: DHHS | B71: daas.utah.gov | C71: Aging & Adult Services – Utah DHHS | Services for Utah's Aging Adults | D71: =IFERROR(__xludf.DUMMYFUNCTION("REGEXEXTRACT(E71, ""^(?:https?:\/\/)?(?:www\.)?([^\/]+)"")"),"daas.utah.gov") -> daas.utah.gov | E71: https://daas.utah.gov | F71: Active (200) | G71: GTM-P334MTZ9 | H71: G-N8LE1HBTT1 | I71: Yes | J71: DHHS - DAAS - daas.utah.gov | K71: =IF(H71="", "", IF(ISNUMBER(_xlfn.XMATCH(H71, 'Viks State Rollup Sheet'!G:G)), "Found in Rollup", "MISSING in Rollup")) -> Found in Rollup
A72: DHHS | B72: dcfs.utah.gov | C72: Child and Family Services – Utah DHHS | Strengthening families. Protecting children. | D72: =IFERROR(__xludf.DUMMYFUNCTION("REGEXEXTRACT(E72, ""^(?:https?:\/\/)?(?:www\.)?([^\/]+)"")"),"dcfs.utah.gov") -> dcfs.utah.gov | E72: https://dcfs.utah.gov | F72: Active (200) | G72: GTM-N6825ZM7 | H72: G-WBTLVBKJKV | I72: Yes | J72: DHHS - DCFS - dcfs.utah.gov | K72: =IF(H72="", "", IF(ISNUMBER(_xlfn.XMATCH(H72, 'Viks State Rollup Sheet'!G:G)), "Found in Rollup", "MISSING in Rollup")) -> Found in Rollup
A73: DHHS | B73: familyhealth.utah.gov | C73: Division of Family Health – Utah DHHS | D73: =IFERROR(__xludf.DUMMYFUNCTION("REGEXEXTRACT(E73, ""^(?:https?:\/\/)?(?:www\.)?([^\/]+)"")"),"familyhealth.utah.gov") -> familyhealth.utah.gov | E73: https://familyhealth.utah.gov | F73: Active (200) | G73: GTM-P48S3973 | H73: G-E9MV39ZQB9 | I73: Yes | J73: DHHS - DFH - familyhealth.utah.gov | K73: =IF(H73="", "", IF(ISNUMBER(_xlfn.XMATCH(H73, 'Viks State Rollup Sheet'!G:G)), "Found in Rollup", "MISSING in Rollup")) -> Found in Rollup
A74: DHHS | B74: mihp.utah.gov | C74: Maternal and Infant Health Program | Utah Department of Health and Human Services | D74: =IFERROR(__xludf.DUMMYFUNCTION("REGEXEXTRACT(E74, ""^(?:https?:\/\/)?(?:www\.)?([^\/]+)"")"),"mihp.utah.gov") -> mihp.utah.gov | E74: https://mihp.utah.gov | F74: Active (200) | G74: GTM-WHHK8Z5N | H74: G-2TKZEJVEDJ | I74: Yes | J74: DHHS - DFH - mihp.utah.gov | K74: =IF(H74="", "", IF(ISNUMBER(_xlfn.XMATCH(H74, 'Viks State Rollup Sheet'!G:G)), "Found in Rollup", "MISSING in Rollup")) -> Found in Rollup
A75: DHHS | B75: catchtheanswers.utah.gov | C75: Catch the Answers – Utah DHHS | D75: =IFERROR(__xludf.DUMMYFUNCTION("REGEXEXTRACT(E75, ""^(?:https?:\/\/)?(?:www\.)?([^\/]+)"")"),"catchtheanswers.utah.gov") -> catchtheanswers.utah.gov | E75: https://catchtheanswers.utah.gov | F75: Active (200) | G75: GTM-PJB3VXNQ | H75: G-9LZTVSQTQD | I75: Yes | J75: DHHS - DPH - catchtheanswers.utah.gov | K75: =IF(H75="", "", IF(ISNUMBER(_xlfn.XMATCH(H75, 'Viks State Rollup Sheet'!G:G)), "Found in Rollup", "MISSING in Rollup")) -> Found in Rollup
A76: DHHS | B76: epi.utah.gov | C76: Communicable Diseases – Utah DHHS | D76: =IFERROR(__xludf.DUMMYFUNCTION("REGEXEXTRACT(E76, ""^(?:https?:\/\/)?(?:www\.)?([^\/]+)"")"),"epi.utah.gov") -> epi.utah.gov | E76: https://epi.utah.gov | F76: Active (200) | G76: GTM-PVL4V6MH | H76: G-9B7PL789LT | I76: Yes | J76: DHHS - DPH - epi.utah.gov | K76: =IF(H76="", "", IF(ISNUMBER(_xlfn.XMATCH(H76, 'Viks State Rollup Sheet'!G:G)), "Found in Rollup", "MISSING in Rollup")) -> Found in Rollup
A77: DHHS | B77: https://heal.utah.gov/ | C77: Healthy Environments Active Living (HEAL) – Utah DHHS | Building Stronger, Healthier Communities | D77: =IFERROR(__xludf.DUMMYFUNCTION("REGEXEXTRACT(E77, ""^(?:https?:\/\/)?(?:www\.)?([^\/]+)"")"),"heal.utah.gov") -> heal.utah.gov | E77: https://heal.utah.gov/ | F77: Active (200) | G77: GTM-KTS4QSJ, GTM-N2BTHBBD | H77: G-2KFRFEPXMJ | I77: Yes | J77: DHHS - DPH - heal.utah.gov | K77: =IF(H77="", "", IF(ISNUMBER(_xlfn.XMATCH(H77, 'Viks State Rollup Sheet'!G:G)), "Found in Rollup", "MISSING in Rollup")) -> Found in Rollup
A78: DHHS | B78: healthyaging.utah.gov | C78: Healthy Aging Program – Utah DHHS | D78: =IFERROR(__xludf.DUMMYFUNCTION("REGEXEXTRACT(E78, ""^(?:https?:\/\/)?(?:www\.)?([^\/]+)"")"),"healthyaging.utah.gov") -> healthyaging.utah.gov | E78: https://healthyaging.utah.gov | F78: Active (200) | G78: GTM-NF3DLWTG | H78: G-1C1QS7FEYT | I78: Yes | J78: DHHS - DPH - Health Aging - healthyaging.utah.gov | K78: =IF(H78="", "", IF(ISNUMBER(_xlfn.XMATCH(H78, 'Viks State Rollup Sheet'!G:G)), "Found in Rollup", "MISSING in Rollup")) -> Found in Rollup
A79: DHHS | B79: hivandme.com | C79: Hiv and Me | D79: =IFERROR(__xludf.DUMMYFUNCTION("REGEXEXTRACT(E79, ""^(?:https?:\/\/)?(?:www\.)?([^\/]+)"")"),"hivandme.com") -> hivandme.com | E79: https://hivandme.com | F79: Active (200) | G79: GTM-M3SZ8NG, GTM-MZV2K26H | H79: G-7J459WBCKX, G-7NCZGBW67T, UA-154674898-1 | I79: Yes | J79: DHHS - DPH - hivandme.com | K79: =IF(H79="", "", IF(ISNUMBER(_xlfn.XMATCH(H79, 'Viks State Rollup Sheet'!G:G)), "Found in Rollup", "MISSING in Rollup")) -> MISSING in Rollup
A80: DHHS | B80: immunize.utah.gov | C80: Immunize | Utah Department of Health and Human Services | D80: =IFERROR(__xludf.DUMMYFUNCTION("REGEXEXTRACT(E80, ""^(?:https?:\/\/)?(?:www\.)?([^\/]+)"")"),"immunize.utah.gov") -> immunize.utah.gov | E80: https://immunize.utah.gov | F80: Active (200) | G80: GTM-589S362, GTM-KB47DSZ8 | H80: G-MTYSY93RJ5 | I80: Yes | J80: DHHS - DPH - immunize.utah.gov | K80: =IF(H80="", "", IF(ISNUMBER(_xlfn.XMATCH(H80, 'Viks State Rollup Sheet'!G:G)), "Found in Rollup", "MISSING in Rollup")) -> Found in Rollup
A81: DHHS | B81: http://healthequity.utah.gov/ | C81: Office of Health Equity | Utah Department of Health and Human Services | D81: =IFERROR(__xludf.DUMMYFUNCTION("REGEXEXTRACT(E81, ""^(?:https?:\/\/)?(?:www\.)?([^\/]+)"")"),"healthequity.utah.gov") -> healthequity.utah.gov | E81: http://healthequity.utah.gov/ | F81: Active (200) | G81: GTM-NV6GT69F | H81: G-R840YB1ELD | I81: Yes | J81: DHHS - DPH - OHE - healthequity.utah.gov | K81: =IF(H81="", "", IF(ISNUMBER(_xlfn.XMATCH(H81, 'Viks State Rollup Sheet'!G:G)), "Found in Rollup", "MISSING in Rollup")) -> Found in Rollup
A82: DHHS | B82: opidemic.utah.gov | C82: Stop the Opidemic | Utah Department of Health and Human Services | D82: =IFERROR(__xludf.DUMMYFUNCTION("REGEXEXTRACT(E82, ""^(?:https?:\/\/)?(?:www\.)?([^\/]+)"")"),"opidemic.utah.gov") -> opidemic.utah.gov | E82: https://opidemic.utah.gov | F82: Active (200) | G82: GTM-559D2B3T | H82: G-1RZ7WKZL6P | I82: Yes | J82: DHHS - DPH - opidemic.utah.gov | K82: =IF(H82="", "", IF(ISNUMBER(_xlfn.XMATCH(H82, 'Viks State Rollup Sheet'!G:G)), "Found in Rollup", "MISSING in Rollup")) -> Found in Rollup
A83: DHHS | B83: https://ruralhealth.utah.gov/ | C83: PCRH | Primary Care and Rural Health Website | D83: =IFERROR(__xludf.DUMMYFUNCTION("REGEXEXTRACT(E83, ""^(?:https?:\/\/)?(?:www\.)?([^\/]+)"")"),"ruralhealth.utah.gov") -> ruralhealth.utah.gov | E83: https://ruralhealth.utah.gov/ | F83: Active (200) | G83: GTM-KQVKGS38 | H83: G-MTBMK34DQC | I83: Yes | J83: DHHS - DPH - Primary Care & Rural Health - ruralhealth.utah.gov | K83: =IF(H83="", "", IF(ISNUMBER(_xlfn.XMATCH(H83, 'Viks State Rollup Sheet'!G:G)), "Found in Rollup", "MISSING in Rollup")) -> Found in Rollup
A84: DHHS | B84: cancer.utah.gov | C84: Utah Cancer Programs – Utah DHHS | D84: =IFERROR(__xludf.DUMMYFUNCTION("REGEXEXTRACT(E84, ""^(?:https?:\/\/)?(?:www\.)?([^\/]+)"")"),"cancer.utah.gov") -> cancer.utah.gov | E84: https://cancer.utah.gov | F84: Active (200) | G84: GTM-NRL6MGJJ | H84: G-8FMRJYPHD8, G-E9MV39ZQB9 | I84: Yes | J84: DHHS - DPH - UBCCP - cancer.utah.gov | DHHS - DFH - familyhealth.utah.gov | K84: =IF(H84="", "", IF(ISNUMBER(_xlfn.XMATCH(H84, 'Viks State Rollup Sheet'!G:G)), "Found in Rollup", "MISSING in Rollup")) -> MISSING in Rollup
A85: DHHS | B85: vipp.utah.gov | C85: Violence and Injury Prevention Program | Utah Department of Health and Human Services | D85: =IFERROR(__xludf.DUMMYFUNCTION("REGEXEXTRACT(E85, ""^(?:https?:\/\/)?(?:www\.)?([^\/]+)"")"),"vipp.utah.gov") -> vipp.utah.gov | E85: https://vipp.utah.gov | F85: Active (200) | G85: GTM-5F6RHQCW | H85: G-EMEVFXJLLG | I85: Yes | J85: DHHS - DPH - vipp.utah.gov | K85: =IF(H85="", "", IF(ISNUMBER(_xlfn.XMATCH(H85, 'Viks State Rollup Sheet'!G:G)), "Found in Rollup", "MISSING in Rollup")) -> Found in Rollup
A86: DHHS | B86: adoptionregistry.utah.gov | C86: Adoption Registry | Utah Department of Health and Human Services | D86: =IFERROR(__xludf.DUMMYFUNCTION("REGEXEXTRACT(E86, ""^(?:https?:\/\/)?(?:www\.)?([^\/]+)"")"),"adoptionregistry.utah.gov") -> adoptionregistry.utah.gov | E86: https://adoptionregistry.utah.gov | F86: Active (200) | G86: GTM-T6NRNNLS | H86: G-XPJDC0ZQX5 | I86: Yes | J86: DHHS - DSE - Adoption Registry | K86: =IF(H86="", "", IF(ISNUMBER(_xlfn.XMATCH(H86, 'Viks State Rollup Sheet'!G:G)), "Found in Rollup", "MISSING in Rollup")) -> Found in Rollup
A87: DHHS | B87: healthassessment.utah.gov | C87: Survey and Health Assessment Programs – Utah DHHS | Office of Research and Evaluation | D87: =IFERROR(__xludf.DUMMYFUNCTION("REGEXEXTRACT(E87, ""^(?:https?:\/\/)?(?:www\.)?([^\/]+)"")"),"healthassessment.utah.gov") -> healthassessment.utah.gov | E87: https://healthassessment.utah.gov | F87: Active (200) | G87: GTM-MLBNFVQM | H87: G-VB62NHJTDS | I87: Yes | J87: DHHS - DSE - Health Workforce Information Center - hwic.utah.gov | K87: =IF(H87="", "", IF(ISNUMBER(_xlfn.XMATCH(H87, 'Viks State Rollup Sheet'!G:G)), "Found in Rollup", "MISSING in Rollup")) -> Found in Rollup
A88: DHHS | B88: healthcarestats.utah.gov | C88: Health Care Statistics Programs – Utah DHHS | D88: =IFERROR(__xludf.DUMMYFUNCTION("REGEXEXTRACT(E88, ""^(?:https?:\/\/)?(?:www\.)?([^\/]+)"")"),"healthcarestats.utah.gov") -> healthcarestats.utah.gov | E88: https://healthcarestats.utah.gov | F88: Active (200) | G88: GTM-W7CPXZZT | H88: G-4DBQPP01P4 | I88: Yes | J88: DHHS - DSE - healthcarestats.utah.gov | K88: =IF(H88="", "", IF(ISNUMBER(_xlfn.XMATCH(H88, 'Viks State Rollup Sheet'!G:G)), "Found in Rollup", "MISSING in Rollup")) -> Found in Rollup
A89: DHHS | B89: patientsafety.utah.gov | C89: Patient Safety Initiatives | Data, Systems, and Evaluation | D89: =IFERROR(__xludf.DUMMYFUNCTION("REGEXEXTRACT(E89, ""^(?:https?:\/\/)?(?:www\.)?([^\/]+)"")"),"patientsafety.utah.gov") -> patientsafety.utah.gov | E89: https://patientsafety.utah.gov | F89: Active (200) | G89: GTM-MZ865N6K | H89: G-SR9T7X7PD2 | I89: Yes | J89: DHHS - DSE - patientsafety.health.utah.gov | K89: =IF(H89="", "", IF(ISNUMBER(_xlfn.XMATCH(H89, 'Viks State Rollup Sheet'!G:G)), "Found in Rollup", "MISSING in Rollup")) -> Found in Rollup
A90: DHHS | B90: vitalrecords.utah.gov | C90: Vital Records | Utah Department of Health and Human Services | Birth, Death, Adoption Records and Other Statistics | D90: =IFERROR(__xludf.DUMMYFUNCTION("REGEXEXTRACT(E90, ""^(?:https?:\/\/)?(?:www\.)?([^\/]+)"")"),"vitalrecords.utah.gov") -> vitalrecords.utah.gov | E90: https://vitalrecords.utah.gov | F90: Active (200) | G90: GTM-N8L4ZBQB | H90: G-N8SDN6QB9N | I90: Yes | J90: DHHS - DSE - vitalrecords.utah.gov | K90: =IF(H90="", "", IF(ISNUMBER(_xlfn.XMATCH(H90, 'Viks State Rollup Sheet'!G:G)), "Found in Rollup", "MISSING in Rollup")) -> Found in Rollup
A91: DHHS | B91: dspd.utah.gov | C91: Services for People with Disabilities – Utah DHHS | D91: =IFERROR(__xludf.DUMMYFUNCTION("REGEXEXTRACT(E91, ""^(?:https?:\/\/)?(?:www\.)?([^\/]+)"")"),"dspd.utah.gov") -> dspd.utah.gov | E91: https://dspd.utah.gov | F91: Active (200) | G91: GTM-K292V8Z4 | H91: G-E5MRG90E2V | I91: Yes | J91: DHHS - DSPD - dspd.utah.gov | K91: =IF(H91="", "", IF(ISNUMBER(_xlfn.XMATCH(H91, 'Viks State Rollup Sheet'!G:G)), "Found in Rollup", "MISSING in Rollup")) -> Found in Rollup
A92: DHHS | B92: usdc.utah.gov | C92: Utah State Development Center | Utah Department of Health and Human Services | D92: =IFERROR(__xludf.DUMMYFUNCTION("REGEXEXTRACT(E92, ""^(?:https?:\/\/)?(?:www\.)?([^\/]+)"")"),"usdc.utah.gov") -> usdc.utah.gov | E92: https://usdc.utah.gov | F92: Active (200) | G92: GTM-TW9FZZNV | H92: G-6MGGZ7T9XQ | I92: Yes | J92: DHHS - DSPD - Utah State Developmental Center - usdc.utah.gov | K92: =IF(H92="", "", IF(ISNUMBER(_xlfn.XMATCH(H92, 'Viks State Rollup Sheet'!G:G)), "Found in Rollup", "MISSING in Rollup")) -> Found in Rollup
A93: DHHS | B93: https://coveringkids.utah.gov/ | C93: Covering Kids – Utah DHHS | CHIP and Medicaid for Utah Kids | D93: =IFERROR(__xludf.DUMMYFUNCTION("REGEXEXTRACT(E93, ""^(?:https?:\/\/)?(?:www\.)?([^\/]+)"")"),"coveringkids.utah.gov") -> coveringkids.utah.gov | E93: https://coveringkids.utah.gov/ | F93: Active (200) | G93: GTM-52W6B4G5, GTM-N59FGF3 | H93: G-XDWJGGX4J4, UA-82792758-12 | I93: Yes | J93: DHHS - IH - coveringkids.utah.gov | K93: =IF(H93="", "", IF(ISNUMBER(_xlfn.XMATCH(H93, 'Viks State Rollup Sheet'!G:G)), "Found in Rollup", "MISSING in Rollup")) -> MISSING in Rollup
A94: DHHS | B94: https://healthyminds.utah.gov/ | C94: Healthy Minds – Utah DHHS | D94: =IFERROR(__xludf.DUMMYFUNCTION("REGEXEXTRACT(E94, ""^(?:https?:\/\/)?(?:www\.)?([^\/]+)"")"),"healthyminds.utah.gov") -> healthyminds.utah.gov | E94: https://healthyminds.utah.gov/ | F94: Active (200) | G94: GTM-W28FNH6F | H94: G-JKJD7FDXHR | I94: Yes | J94: DHHS - IH - Healthy Minds - healthyminds.utah.gov | K94: =IF(H94="", "", IF(ISNUMBER(_xlfn.XMATCH(H94, 'Viks State Rollup Sheet'!G:G)), "Found in Rollup", "MISSING in Rollup")) -> Found in Rollup
A95: DHHS | B95: medicaid.utah.gov | C95: Medicaid - Utah DHHS | D95: =IFERROR(__xludf.DUMMYFUNCTION("REGEXEXTRACT(E95, ""^(?:https?:\/\/)?(?:www\.)?([^\/]+)"")"),"medicaid.utah.gov") -> medicaid.utah.gov | E95: https://medicaid.utah.gov | F95: Active (200) | G95: GTM-55C5RNR5 | H95: G-YNY7E7MRM7 | I95: Yes | J95: DHHS - IH - medicaid.utah.gov | K95: =IF(H95="", "", IF(ISNUMBER(_xlfn.XMATCH(H95, 'Viks State Rollup Sheet'!G:G)), "Found in Rollup", "MISSING in Rollup")) -> Found in Rollup
A96: DHHS | B96: sumh.utah.gov | C96: Substance Use and Mental Health | Utah Department of Health and Human Services | D96: =IFERROR(__xludf.DUMMYFUNCTION("REGEXEXTRACT(E96, ""^(?:https?:\/\/)?(?:www\.)?([^\/]+)"")"),"sumh.utah.gov") -> sumh.utah.gov | E96: https://sumh.utah.gov | F96: Active (200) | G96: GTM-TMLXC9XN | H96: G-WYEPYF677M | I96: Yes | J96: DHHS - IH - SUMH - sumh.utah.gov | K96: =IF(H96="", "", IF(ISNUMBER(_xlfn.XMATCH(H96, 'Viks State Rollup Sheet'!G:G)), "Found in Rollup", "MISSING in Rollup")) -> MISSING in Rollup
A97: DHHS | B97: ush.utah.gov | C97: Utah State Hospital | Utah Department of Health and Human Services | Mental Illness treatment in a safe and healing environment. | D97: =IFERROR(__xludf.DUMMYFUNCTION("REGEXEXTRACT(E97, ""^(?:https?:\/\/)?(?:www\.)?([^\/]+)"")"),"ush.utah.gov") -> ush.utah.gov | E97: https://ush.utah.gov | F97: Active (200) | G97: GTM-MFKRJKDD | H97: G-R16NL3X6JB | I97: Yes | J97: DHHS - IH - Utah State Hospital - ush.utah.gov | K97: =IF(H97="", "", IF(ISNUMBER(_xlfn.XMATCH(H97, 'Viks State Rollup Sheet'!G:G)), "Found in Rollup", "MISSING in Rollup")) -> Found in Rollup
A98: DHHS | B98: http://dhhs.utah.gov/ | C98: Utah Department of Health and Human Services | D98: =IFERROR(__xludf.DUMMYFUNCTION("REGEXEXTRACT(E98, ""^(?:https?:\/\/)?(?:www\.)?([^\/]+)"")"),"dhhs.utah.gov") -> dhhs.utah.gov | E98: http://dhhs.utah.gov/ | F98: Active (200) | G98: GTM-KGKVG6XQ | H98: G-1ZJX6VCK1J | I98: Yes | J98: DHHS - Main - dhhs.utah.gov | K98: =IF(H98="", "", IF(ISNUMBER(_xlfn.XMATCH(H98, 'Viks State Rollup Sheet'!G:G)), "Found in Rollup", "MISSING in Rollup")) -> Found in Rollup
A99: DHHS | B99: Office of Ombuds - Department of Health and Human Services | C99: Office of Ombuds - Department of Health and Human Services | D99: =IFERROR(__xludf.DUMMYFUNCTION("REGEXEXTRACT(E99, ""^(?:https?:\/\/)?(?:www\.)?([^\/]+)"")"),"dhhs.utah.gov") -> dhhs.utah.gov | E99: https://dhhs.utah.gov/ombuds-services/ | F99: No Original Link | G99: GTM-KGKVG6XQ, GTM-NPWBCNVZ | H99: G-1ZJX6VCK1J | I99: Yes | J99: DHHS - Main - dhhs.utah.gov | K99: =IF(H99="", "", IF(ISNUMBER(_xlfn.XMATCH(H99, 'Viks State Rollup Sheet'!G:G)), "Found in Rollup", "MISSING in Rollup")) -> Found in Rollup
A100: DHHS | B100: ome.utah.gov | C100: Office of the Medical Examiner | Utah Department of Health and Human Services | D100: =IFERROR(__xludf.DUMMYFUNCTION("REGEXEXTRACT(E100, ""^(?:https?:\/\/)?(?:www\.)?([^\/]+)"")"),"ome.utah.gov") -> ome.utah.gov | E100: https://ome.utah.gov | F100: Active (200) | G100: GTM-P8CBGPFV | H100: G-KFN6GS5XFR | I100: Yes | J100: DHHS - Office of Medical Examiner - ome.utah.gov | K100: =IF(H100="", "", IF(ISNUMBER(_xlfn.XMATCH(H100, 'Viks State Rollup Sheet'!G:G)), "Found in Rollup", "MISSING in Rollup")) -> Found in Rollup
...

Sheet Sheet12

Sheet State Google Tags on Account
A1: GA360_Property_Name | B1: GA360_Property_ID | C1: Stream_Name | D1: Stream_URL | E1: Measurement_ID | F1: Missing
A2: DGO - DHRM - Offer Acceptance | B2: 254102168 | C2: Offer Acceptance | D2: https://offeracceptance.utah.gov/ | E2: G-SHRVL5TZ37 | F2: =IF(E2="", "", IF(ISNUMBER(_xlfn.XMATCH(E2, 'Champions Sheet'!H:H)), "Found in Master", "MISSING in Alicia's")) -> MISSING in Alicia's
A3: DOC - DOPL - UPHP | B3: 255775667 | C3: UPHP website | D3: https://uphp.utah.gov/ | E3: G-RTV6KNP85X | F3: =IF(E3="", "", IF(ISNUMBER(_xlfn.XMATCH(E3, 'Champions Sheet'!H:H)), "Found in Master", "MISSING in Alicia's")) -> MISSING in Alicia's
A4: CCE - AM - Museum Social Impact | B4: 258064736 | C4: Museum Social Impact Website | D4: https://museumsocialimpact.org | E4: G-4ERD645EY8 | F4: =IF(E4="", "", IF(ISNUMBER(_xlfn.XMATCH(E4, 'Champions Sheet'!H:H)), "Found in Master", "MISSING in Alicia's")) -> MISSING in Alicia's
A5: UDOT - Trucksmart - trucksmart.udot.utah.gov | B5: 263913003 | C5: Trucksmart 2021 | D5: https://trucksmart.udot.utah.gov | E5: G-JM4TGYJ7Y3 | F5: =IF(E5="", "", IF(ISNUMBER(_xlfn.XMATCH(E5, 'Champions Sheet'!H:H)), "Found in Master", "MISSING in Alicia's")) -> MISSING in Alicia's
A6: UDOT - Zero Fatalities - zerofatalities.com | B6: 268026917 | C6: Zero Fatalities - GA4 | D6: https://zerofatalities.com | E6: G-W74DBWG5TL | F6: =IF(E6="", "", IF(ISNUMBER(_xlfn.XMATCH(E6, 'Champions Sheet'!H:H)), "Found in Master", "MISSING in Alicia's")) -> MISSING in Alicia's
A7: DEQ - Main Website | B7: 270736262 | C7: deq.utah.gov - GA4 | D7: https://deq.utah.gov | E7: G-RRTEGT2P5N | F7: =IF(E7="", "", IF(ISNUMBER(_xlfn.XMATCH(E7, 'Champions Sheet'!H:H)), "Found in Master", "MISSING in Alicia's")) -> Found in Master
A8: DEQ - DAQ - Monitoring App | B8: 271285752 | C8: AQ Monitoring - GA4 | D8: https://air.utah.gov | E8: G-YTMMRM6RBF | F8: =IF(E8="", "", IF(ISNUMBER(_xlfn.XMATCH(E8, 'Champions Sheet'!H:H)), "Found in Master", "MISSING in Alicia's")) -> MISSING in Alicia's
A9: CCE - Intranet | B9: 272286753 | C9: CCE - Intranet | D9: https://cceintranet.utah.gov | E9: G-6HVSGMMQCC | F9: =IF(E9="", "", IF(ISNUMBER(_xlfn.XMATCH(E9, 'Champions Sheet'!H:H)), "Found in Master", "MISSING in Alicia's")) -> MISSING in Alicia's
A10: CCE - Main Website | B10: 272291754 | C10: CCE - Community | D10: https://community.utah.gov | E10: G-GV5EBLNQCZ | F10: =IF(E10="", "", IF(ISNUMBER(_xlfn.XMATCH(E10, 'Champions Sheet'!H:H)), "Found in Master", "MISSING in Alicia's")) -> Found in Master
A11: DEQ - DAQ - Permitting App | B11: 272372086 | C11: AQ Permitting - GA4 | D11: https://daqpermitting.utah.gov | E11: G-0HM105CNL9 | F11: =IF(E11="", "", IF(ISNUMBER(_xlfn.XMATCH(E11, 'Champions Sheet'!H:H)), "Found in Master", "MISSING in Alicia's")) -> Found in Master
A12: DOC - Administration | B12: 277811441 | C12: Commerce Administration | D12: https://admin.commerce.utah.gov | E12: G-XTZ95C217Z | F12: =IF(E12="", "", IF(ISNUMBER(_xlfn.XMATCH(E12, 'Champions Sheet'!H:H)), "Found in Master", "MISSING in Alicia's")) -> MISSING in Alicia's
A13: DOC - Blog | B13: 279127117 | C13: Commerce Blog | D13: https://blog.commerce.utah.gov | E13: G-E6HM2EH098 | F13: =IF(E13="", "", IF(ISNUMBER(_xlfn.XMATCH(E13, 'Champions Sheet'!H:H)), "Found in Master", "MISSING in Alicia's")) -> MISSING in Alicia's
... A296: DXP - Test Website - design-system-sandbox.utah.gov | B296: 549457251 | C296: DXP - Test Website - design-system-sandbox.utah.gov/ | D296: https://design-system-sandbox.utah.gov | E296: G-BW1SYM40YP | F296: =IF(E296="", "", IF(ISNUMBER(_xlfn.XMATCH(E296, 'Champions Sheet'!H:H)), "Found in Master", "MISSING in Alicia's")) -> MISSING in Alicia's

Sheet Viks State Rollup Sheet
A1: Account ID | B1: Roll-up Property ID | C1: Roll-up Property Name | D1: Source Property ID | E1: Source Property Name | F1: Source Stream URL(s) | G1: Source Tag ID(s) | H1: In Master Sheet? | I1: Missing in My State API Pull
A2: 295896210 | B2: 488601532 | C2: State of Utah Aggregate - Low Traffic | D2: 346064368 | E2: Attorney General | F2: http://attorneygeneral.utah.gov | G2: G-SF9EQBX4K6 | H2: =IF(G2="", "", IF(ISNUMBER(_xlfn.XMATCH(G2, 'Champions Sheet'!H:H)), "Found in Master", "MISSING in Alicia's")) -> MISSING in Alicia's | I2: =IF(G2="", "", IF(ISNUMBER(_xlfn.XMATCH(G2, 'State Google Tags on Account'!E:E)), "Found in Alicia API Pull", "MISSING in Alicia's API Pull")) -> Found in Alicia API Pull
A3: 295896210 | B3: 450964503 | C3: State of Utah Aggregate | D3: 381643798 | E3: Office of the Utah State Auditor | F3: http://auditor.utah.gov | G3: G-YBQJ163BW5 | H3: =IF(G3="", "", IF(ISNUMBER(_xlfn.XMATCH(G3, 'Champions Sheet'!H:H)), "Found in Master", "MISSING in Alicia's")) -> MISSING in Alicia's | I3: =IF(G3="", "", IF(ISNUMBER(_xlfn.XMATCH(G3, 'State Google Tags on Account'!E:E)), "Found in Alicia API Pull", "MISSING in Alicia's API Pull")) -> Found in Alicia API Pull
A4: 295896210 | B4: 487084052 | C4: DOC - All Public Websites | D4: 331553278 | E4: DOC - All Websites - commerce.utah.gov | F4: http://commerce.utah.gov | G4: G-PZZ62EM49P | H4: =IF(G4="", "", IF(ISNUMBER(_xlfn.XMATCH(G4, 'Champions Sheet'!H:H)), "Found in Master", "MISSING in Alicia's")) -> MISSING in Alicia's | I4: =IF(G4="", "", IF(ISNUMBER(_xlfn.XMATCH(G4, 'State Google Tags on Account'!E:E)), "Found in Alicia API Pull", "MISSING in Alicia's API Pull")) -> Found in Alicia API Pull
A5: 295896210 | B5: 450964503 | C5: State of Utah Aggregate | D5: 331553278 | E5: DOC - All Websites - commerce.utah.gov | F5: http://commerce.utah.gov | G5: G-PZZ62EM49P | H5: =IF(G5="", "", IF(ISNUMBER(_xlfn.XMATCH(G5, 'Champions Sheet'!H:H)), "Found in Master", "MISSING in Alicia's")) -> MISSING in Alicia's | I5: =IF(G5="", "", IF(ISNUMBER(_xlfn.XMATCH(G5, 'State Google Tags on Account'!E:E)), "Found in Alicia API Pull", "MISSING in Alicia's API Pull")) -> Found in Alicia API Pull
A6: 295896210 | B6: 487084052 | C6: DOC - All Public Websites | D6: 331579917 | E6: DOC - CORP | F6: http://corporations.utah.gov | G6: G-RED8SLHVQ3 | H6: =IF(G6="", "", IF(ISNUMBER(_xlfn.XMATCH(G6, 'Champions Sheet'!H:H)), "Found in Master", "MISSING in Alicia's")) -> MISSING in Alicia's | I6: =IF(G6="", "", IF(ISNUMBER(_xlfn.XMATCH(G6, 'State Google Tags on Account'!E:E)), "Found in Alicia API Pull", "MISSING in Alicia's API Pull")) -> Found in Alicia API Pull
A7: 295896210 | B7: 450964503 | C7: State of Utah Aggregate | D7: 331579917 | E7: DOC - CORP | F7: http://corporations.utah.gov | G7: G-RED8SLHVQ3 | H7: =IF(G7="", "", IF(ISNUMBER(_xlfn.XMATCH(G7, 'Champions Sheet'!H:H)), "Found in Master", "MISSING in Alicia's")) -> MISSING in Alicia's | I7: =IF(G7="", "", IF(ISNUMBER(_xlfn.XMATCH(G7, 'State Google Tags on Account'!E:E)), "Found in Alicia API Pull", "MISSING in Alicia's API Pull")) -> Found in Alicia API Pull
A8: 295896210 | B8: 488601532 | C8: State of Utah Aggregate - Low Traffic | D8: 346115405 | E8: CCJJ - UOVC | F8: http://crimevictim.utah.gov/ | G8: G-2NQRP84TH7 | H8: =IF(G8="", "", IF(ISNUMBER(_xlfn.XMATCH(G8, 'Champions Sheet'!H:H)), "Found in Master", "MISSING in Alicia's")) -> Found in Master | I8: =IF(G8="", "", IF(ISNUMBER(_xlfn.XMATCH(G8, 'State Google Tags on Account'!E:E)), "Found in Alicia API Pull", "MISSING in Alicia's API Pull")) -> Found in Alicia API Pull
A9: 295896210 | B9: 487084052 | C9: DOC - All Public Websites | D9: 331609147 | E9: DOC - DCP, OCS, DRE | F9: http://dcp.utah.gov/ | G9: G-CVR3K81XQZ | H9: =IF(G9="", "", IF(ISNUMBER(_xlfn.XMATCH(G9, 'Champions Sheet'!H:H)), "Found in Master", "MISSING in Alicia's")) -> MISSING in Alicia's | I9: =IF(G9="", "", IF(ISNUMBER(_xlfn.XMATCH(G9, 'State Google Tags on Account'!E:E)), "Found in Alicia API Pull", "MISSING in Alicia's API Pull")) -> Found in Alicia API Pull
A10: 295896210 | B10: 450964503 | C10: State of Utah Aggregate | D10: 331609147 | E10: DOC - DCP, OCS, DRE | F10: http://dcp.utah.gov/ | G10: G-CVR3K81XQZ | H10: =IF(G10="", "", IF(ISNUMBER(_xlfn.XMATCH(G10, 'Champions Sheet'!H:H)), "Found in Master", "MISSING in Alicia's")) -> MISSING in Alicia's | I10: =IF(G10="", "", IF(ISNUMBER(_xlfn.XMATCH(G10, 'State Google Tags on Account'!E:E)), "Found in Alicia API Pull", "MISSING in Alicia's API Pull")) -> Found in Alicia API Pull
A11: 295896210 | B11: 450964503 | C11: State of Utah Aggregate | D11: 385127374 | E11: LG - Elections - Disclosures | F11: http://disclosures.utah.gov | G11: G-3BSQB369FR | H11: =IF(G11="", "", IF(ISNUMBER(_xlfn.XMATCH(G11, 'Champions Sheet'!H:H)), "Found in Master", "MISSING in Alicia's")) -> MISSING in Alicia's | I11: =IF(G11="", "", IF(ISNUMBER(_xlfn.XMATCH(G11, 'State Google Tags on Account'!E:E)), "Found in Alicia API Pull", "MISSING in Alicia's API Pull")) -> Found in Alicia API Pull
A12: 295896210 | B12: 482352716 | C12: DHHS - Roll-up - All properties | D12: 346275491 | E12: DHHS - DLBC - dlbc.utah.gov | F12: http://dlbc.utah.gov | G12: G-Z8E586EN9V | H12: =IF(G12="", "", IF(ISNUMBER(_xlfn.XMATCH(G12, 'Champions Sheet'!H:H)), "Found in Master", "MISSING in Alicia's")) -> MISSING in Alicia's | I12: =IF(G12="", "", IF(ISNUMBER(_xlfn.XMATCH(G12, 'State Google Tags on Account'!E:E)), "Found in Alicia API Pull", "MISSING in Alicia's API Pull")) -> Found in Alicia API Pull
A13: 295896210 | B13: 450964503 | C13: State of Utah Aggregate | D13: 346275491 | E13: DHHS - DLBC - dlbc.utah.gov | F13: http://dlbc.utah.gov | G13: G-Z8E586EN9V | H13: =IF(G13="", "", IF(ISNUMBER(_xlfn.XMATCH(G13, 'Champions Sheet'!H:H)), "Found in Master", "MISSING in Alicia's")) -> MISSING in Alicia's | I13: =IF(G13="", "", IF(ISNUMBER(_xlfn.XMATCH(G13, 'State Google Tags on Account'!E:E)), "Found in Alicia API Pull", "MISSING in Alicia's API Pull")) -> Found in Alicia API Pull
... A19: 295896210 | B19: 450964503 | C19: State of Utah Aggregate | D19: 346745177 | E19: DHHS - DSPD - dspd.utah.gov | F19: http://dspd.utah.gov | G19: G-E5MRG90E2V | H19: =IF(G19="", "", IF(ISNUMBER(_xlfn.XMATCH(G19, 'Champions Sheet'!H:H)), "Found in Master", "MISSING in Alicia's")) -> Found in Master | I19: =IF(G19="", "", IF(ISNUMBER(_xlfn.XMATCH(G19, 'State Google Tags on Account'!E:E)), "Found in Alicia API Pull", "MISSING in Alicia's API Pull")) -> Found in Alicia API Pull
A20: 295896210 | B20: 482151148 | C20: DNR - All Websites | D20: 324057916 | E20: DNR - DWR - Recreation access | F20: http://dwrapps.utah.gov/ram/start2, https://dwrapps.utah.gov/events | G20: G-11Y80DXQRJ, G-0GSTKZMBKS | H20: =IF(G20="", "", IF(ISNUMBER(_xlfn.XMATCH(G20, 'Champions Sheet'!H:H)), "Found in Master", "MISSING in Alicia's")) -> MISSING in Alicia's | I20: Manually found only G-0GSTKZMBKS
A21: 295896210 | B21: 450964503 | C21: State of Utah Aggregate | D21: 324057916 | E21: DNR - DWR - Recreation access | F21: http://dwrapps.utah.gov/ram/start2, https://dwrapps.utah.gov/events | G21: G-11Y80DXQRJ, G-0GSTKZMBKS | H21: =IF(G21="", "", IF(ISNUMBER(_xlfn.XMATCH(G21, 'Champions Sheet'!H:H)), "Found in Master", "MISSING in Alicia's")) -> MISSING in Alicia's | I21: Manually found only G-0GSTKZMBKS
A22: 295896210 | B22: 482151148 | C22: DNR - All Websites | D22: 331548960 | E22: DNR - WRe - Opendata | F22: http://dwre-utahdnr.opendata.arcgis.com/ | G22: G-HTG1PCPGHN | H22: =IF(G22="", "", IF(ISNUMBER(_xlfn.XMATCH(G22, 'Champions Sheet'!H:H)), "Found in Master", "MISSING in Alicia's")) -> MISSING in Alicia's | I22: =IF(G22="", "", IF(ISNUMBER(_xlfn.XMATCH(G22, 'State Google Tags on Account'!E:E)), "Found in Alicia API Pull", "MISSING in Alicia's API Pull")) -> Found in Alicia API Pull
A23: 295896210 | B23: 450964503 | C23: State of Utah Aggregate | D23: 331548960 | E23: DNR - WRe - Opendata | F23: http://dwre-utahdnr.opendata.arcgis.com/ | G23: G-HTG1PCPGHN | H23: =IF(G23="", "", IF(ISNUMBER(_xlfn.XMATCH(G23, 'Champions Sheet'!H:H)), "Found in Master", "MISSING in Alicia's")) -> MISSING in Alicia's | I23: =IF(G23="", "", IF(ISNUMBER(_xlfn.XMATCH(G23, 'State Google Tags on Account'!E:E)), "Found in Alicia API Pull", "MISSING in Alicia's API Pull")) -> Found in Alicia API Pull
A24: 295896210 | B24: 450964503 | C24: State of Utah Aggregate | D24: 362376887 | E24: LG - Election Results | F24: http://electionresults.utah.gov/ | G24: G-MJKWT53WEH | H24: =IF(G24="", "", IF(ISNUMBER(_xlfn.XMATCH(G24, 'Champions Sheet'!H:H)), "Found in Master", "MISSING in Alicia's")) -> MISSING in Alicia's | I24: =IF(G24="", "", IF(ISNUMBER(_xlfn.XMATCH(G24, 'State Google Tags on Account'!E:E)), "Found in Alicia API Pull", "MISSING in Alicia's API Pull")) -> Found in Alicia API Pull
A25: 295896210 | B25: 487657823 | C25: DPS - All Websites | D25: 362601737 | E25: DPS - EMS | F25: http://ems.utah.gov | G25: G-QT6PQS2CRD | H25: =IF(G25="", "", IF(ISNUMBER(_xlfn.XMATCH(G25, 'Champions Sheet'!H:H)), "Found in Master", "MISSING in Alicia's")) -> MISSING in Alicia's | I25: =IF(G25="", "", IF(ISNUMBER(_xlfn.XMATCH(G25, 'State Google Tags on Account'!E:E)), "Found in Alicia API Pull", "MISSING in Alicia's API Pull")) -> Found in Alicia API Pull
A26: 295896210 | B26: 450964503 | C26: State of Utah Aggregate | D26: 362601737 | E26: DPS - EMS | F26: http://ems.utah.gov | G26: G-QT6PQS2CRD | H26: =IF(G26="", "", IF(ISNUMBER(_xlfn.XMATCH(G26, 'Champions Sheet'!H:H)), "Found in Master", "MISSING in Alicia's")) -> MISSING in Alicia's | I26: =IF(G26="", "", IF(ISNUMBER(_xlfn.XMATCH(G26, 'State Google Tags on Account'!E:E)), "Found in Alicia API Pull", "MISSING in Alicia's API Pull")) -> Found in Alicia API Pull
A27: 295896210 | B27: 482151148 | C27: DNR - All Websites | D27: 346726586 | E27: DNR - OED | F27: http://energy.utah.gov | G27: G-8F73JSYN4N | H27: =IF(G27="", "", IF(ISNUMBER(_xlfn.XMATCH(G27, 'Champions Sheet'!H:H)), "Found in Master", "MISSING in Alicia's")) -> Found in Master | I27: =IF(G27="", "", IF(ISNUMBER(_xlfn.XMATCH(G27, 'State Google Tags on Account'!E:E)), "Found in Alicia API Pull", "MISSING in Alicia's API Pull")) -> Found in Alicia API Pull
A28: 295896210 | B28: 450964503 | C28: State of Utah Aggregate | D28: 346726586 | E28: DNR - OED | F28: http://energy.utah.gov | G28: G-8F73JSYN4N | H28: =IF(G28="", "", IF(ISNUMBER(_xlfn.XMATCH(G28, 'Champions Sheet'!H:H)), "Found in Master", "MISSING in Alicia's")) -> Found in Master | I28: =IF(G28="", "", IF(ISNUMBER(_xlfn.XMATCH(G28, 'State Google Tags on Account'!E:E)), "Found in Alicia API Pull", "MISSING in Alicia's API Pull")) -> Found in Alicia API Pull
A29: 295896210 | B29: 483039742 | C29: DGO - All Websites | D29: 367864194 | E29: DGO - Ethics | F29: http://ethics.utah.gov/ | G29: G-F8VR9SLJYS | H29: =IF(G29="", "", IF(ISNUMBER(_xlfn.XMATCH(G29, 'Champions Sheet'!H:H)), "Found in Master", "MISSING in Alicia's")) -> MISSING in Alicia's | I29: =IF(G29="", "", IF(ISNUMBER(_xlfn.XMATCH(G29, 'State Google Tags on Account'!E:E)), "Found in Alicia API Pull", "MISSING in Alicia's API Pull")) -> Found in Alicia API Pull
A30: 295896210 | B30: 488601532 | C30: State of Utah Aggregate - Low Traffic | D30: 367864194 | E30: DGO - Ethics | F30: http://ethics.utah.gov/ | G30: G-F8VR9SLJYS | H30: =IF(G30="", "", IF(ISNUMBER(_xlfn.XMATCH(G30, 'Champions Sheet'!H:H)), "Found in Master", "MISSING in Alicia's")) -> MISSING in Alicia's | I30: =IF(G30="", "", IF(ISNUMBER(_xlfn.XMATCH(G30, 'State Google Tags on Account'!E:E)), "Found in Alicia API Pull", "MISSING in Alicia's API Pull")) -> Found in Alicia API Pull
A31: 295896210 | B31: 482352716 | C31: DHHS - Roll-up - All properties | D31: 346731853 | E31: DHHS - JJYS - jjys.utah.gov | F31: http://jjys.utah.gov | G31: G-XC34LG48EN | H31: =IF(G31="", "", IF(ISNUMBER(_xlfn.XMATCH(G31, 'Champions Sheet'!H:H)), "Found in Master", "MISSING in Alicia's")) -> MISSING in Alicia's | I31: =IF(G31="", "", IF(ISNUMBER(_xlfn.XMATCH(G31, 'State Google Tags on Account'!E:E)), "Found in Alicia API Pull", "MISSING in Alicia's API Pull")) -> Found in Alicia API Pull
A32: 295896210 | B32: 450964503 | C32: State of Utah Aggregate | D32: 346731853 | E32: DHHS - JJYS - jjys.utah.gov | F32: http://jjys.utah.gov | G32: G-XC34LG48EN | H32: =IF(G32="", "", IF(ISNUMBER(_xlfn.XMATCH(G32, 'Champions Sheet'!H:H)), "Found in Master", "MISSING in Alicia's")) -> MISSING in Alicia's | I32: =IF(G32="", "", IF(ISNUMBER(_xlfn.XMATCH(G32, 'State Google Tags on Account'!E:E)), "Found in Alicia API Pull", "MISSING in Alicia's API Pull")) -> Found in Alicia API Pull
A33: 295896210 | B33: 488601532 | C33: State of Utah Aggregate - Low Traffic | D33: 385235281 | E33: CCJJ - Judicial Vacancy | F33: http://judicialvacancy.utah.gov/ | G33: G-PCZY0K8JQG | H33: =IF(G33="", "", IF(ISNUMBER(_xlfn.XMATCH(G33, 'Champions Sheet'!H:H)), "Found in Master", "MISSING in Alicia's")) -> MISSING in Alicia's | I33: =IF(G33="", "", IF(ISNUMBER(_xlfn.XMATCH(G33, 'State Google Tags on Account'!E:E)), "Found in Alicia API Pull", "MISSING in Alicia's API Pull")) -> Found in Alicia API Pull
... A202: 295896210 | B202: 450964503 | C202: State of Utah Aggregate | D202: 433435376 | E202: DGO - DHRM - Gateway | F202: https://gateway.utah.gov | G202: G-5S6VBKNTH9 | H202: =IF(G202="", "", IF(ISNUMBER(_xlfn.XMATCH(G202, 'Champions Sheet'!H:H)), "Found in Master", "MISSING in Alicia's")) -> MISSING in Alicia's | I202: =IF(G202="", "", IF(ISNUMBER(_xlfn.XMATCH(G202, 'State Google Tags on Account'!E:E)), "Found in Alicia API Pull", "MISSING in Alicia's API Pull")) -> Found in Alicia API Pull
A203: 295896210 | B203: 482151148 | C203: DNR - All Websites | D203: 370585777 | E203: DNR - UGS | F203: https://geology.utah.gov, https://geology.utah.gov | G203: G-983EZBYB1K, G-EN4LC4Q69P | H203: =IF(G203="", "", IF(ISNUMBER(_xlfn.XMATCH(G203, 'Champions Sheet'!H:H)), "Found in Master", "MISSING in Alicia's")) -> MISSING in Alicia's | I203: Manually only found G-EN4LC4Q69P
A204: 295896210 | B204: 450964503 | C204: State of Utah Aggregate | D204: 370585777 | E204: DNR - UGS | F204: https://geology.utah.gov, https://geology.utah.gov | G204: G-983EZBYB1K, G-EN4LC4Q69P | H204: =IF(G204="", "", IF(ISNUMBER(_xlfn.XMATCH(G204, 'Champions Sheet'!H:H)), "Found in Master", "MISSING in Alicia's")) -> MISSING in Alicia's | I204: =IF(G204="", "", IF(ISNUMBER(_xlfn.XMATCH(G204, 'State Google Tags on Account'!E:E)), "Found in Alicia API Pull", "MISSING in Alicia's API Pull")) -> MISSING in Alicia's API Pull
A205: 295896210 | B205: 450964503 | C205: State of Utah Aggregate | D205: 365089704 | E205: GOPB - Main Website | F205: https://gomb.utah.gov | G205: G-DZYWHQZP43 | H205: =IF(G205="", "", IF(ISNUMBER(_xlfn.XMATCH(G205, 'Champions Sheet'!H:H)), "Found in Master", "MISSING in Alicia's")) -> MISSING in Alicia's | I205: =IF(G205="", "", IF(ISNUMBER(_xlfn.XMATCH(G205, 'State Google Tags on Account'!E:E)), "Found in Alicia API Pull", "MISSING in Alicia's API Pull")) -> Found in Alicia API Pull
A206: 295896210 | B206: 450964503 | C206: State of Utah Aggregate | D206: 468255943 | E206: GOV - Governor's Office | F206: https://governor.utah.gov | G206: G-4FL295WNP8 | H206: =IF(G206="", "", IF(ISNUMBER(_xlfn.XMATCH(G206, 'Champions Sheet'!H:H)), "Found in Master", "MISSING in Alicia's")) -> MISSING in Alicia's | I206: =IF(G206="", "", IF(ISNUMBER(_xlfn.XMATCH(G206, 'State Google Tags on Account'!E:E)), "Found in Alicia API Pull", "MISSING in Alicia's API Pull")) -> Found in Alicia API Pull
A207: 295896210 | B207: 483039742 | C207: DGO - All Websites | D207: 433479223 | E207: DGO - Main Website | F207: https://govops.utah.gov | G207: G-G8NLKD6M0E | H207: =IF(G207="", "", IF(ISNUMBER(_xlfn.XMATCH(G207, 'Champions Sheet'!H:H)), "Found in Master", "MISSING in Alicia's")) -> MISSING in Alicia's | I207: =IF(G207="", "", IF(ISNUMBER(_xlfn.XMATCH(G207, 'State Google Tags on Account'!E:E)), "Found in Alicia API Pull", "MISSING in Alicia's API Pull")) -> Found in Alicia API Pull
A208: 295896210 | B208: 450964503 | C208: State of Utah Aggregate | D208: 433479223 | E208: DGO - Main Website | F208: https://govops.utah.gov | G208: G-G8NLKD6M0E | H208: =IF(G208="", "", IF(ISNUMBER(_xlfn.XMATCH(G208, 'Champions Sheet'!H:H)), "Found in Master", "MISSING in Alicia's")) -> MISSING in Alicia's | I208: =IF(G208="", "", IF(ISNUMBER(_xlfn.XMATCH(G208, 'State Google Tags on Account'!E:E)), "Found in Alicia API Pull", "MISSING in Alicia's API Pull")) -> Found in Alicia API Pull
A209: 295896210 | B209: 482352716 | C209: DHHS - Roll-up - All properties | D209: 487354183 | E209: DHHS - Gray Matters - graymatters.utah.gov | F209: https://graymatters.utah.gov | G209: G-D9P8778J31 | H209: =IF(G209="", "", IF(ISNUMBER(_xlfn.XMATCH(G209, 'Champions Sheet'!H:H)), "Found in Master", "MISSING in Alicia's")) -> MISSING in Alicia's | I209: =IF(G209="", "", IF(ISNUMBER(_xlfn.XMATCH(G209, 'State Google Tags on Account'!E:E)), "Found in Alicia API Pull", "MISSING in Alicia's API Pull")) -> Found in Alicia API Pull
A210: 295896210 | B210: 450964503 | C210: State of Utah Aggregate | D210: 487354183 | E210: DHHS - Gray Matters - graymatters.utah.gov | F210: https://graymatters.utah.gov | G210: G-D9P8778J31 | H210: =IF(G210="", "", IF(ISNUMBER(_xlfn.XMATCH(G210, 'Champions Sheet'!H:H)), "Found in Master", "MISSING in Alicia's")) -> MISSING in Alicia's | I210: =IF(G210="", "", IF(ISNUMBER(_xlfn.XMATCH(G210, 'State Google Tags on Account'!E:E)), "Found in Alicia API Pull", "MISSING in Alicia's API Pull")) -> Found in Alicia API Pull
A211: 295896210 | B211: 482151148 | C211: DNR - All Websites | D211: 335396203 | E211: DNR - greatsaltlake.utah.gov | F211: https://greatsaltlake.utah.gov | G211: G-MZ312296YY | H211: =IF(G211="", "", IF(ISNUMBER(_xlfn.XMATCH(G211, 'Champions Sheet'!H:H)), "Found in Master", "MISSING in Alicia's")) -> MISSING in Alicia's | I211: =IF(G211="", "", IF(ISNUMBER(_xlfn.XMATCH(G211, 'State Google Tags on Account'!E:E)), "Found in Alicia API Pull", "MISSING in Alicia's API Pull")) -> Found in Alicia API Pull
A212: 295896210 | B212: 450964503 | C212: State of Utah Aggregate | D212: 335396203 | E212: DNR - greatsaltlake.utah.gov | F212: https://greatsaltlake.utah.gov | G212: G-MZ312296YY | H212: =IF(G212="", "", IF(ISNUMBER(_xlfn.XMATCH(G212, 'Champions Sheet'!H:H)), "Found in Master", "MISSING in Alicia's")) -> MISSING in Alicia's | I212: =IF(G212="", "", IF(ISNUMBER(_xlfn.XMATCH(G212, 'State Google Tags on Account'!E:E)), "Found in Alicia API Pull", "MISSING in Alicia's API Pull")) -> Found in Alicia API Pull
A213: 295896210 | B213: 450964503 | C213: State of Utah Aggregate | D213: 461167456 | E213: UNG - Main Website | F213: https://guard.utah.gov | G213: G-RM6WCDG2H3 | H213: =IF(G213="", "", IF(ISNUMBER(_xlfn.XMATCH(G213, 'Champions Sheet'!H:H)), "Found in Master", "MISSING in Alicia's")) -> Found in Master | I213: =IF(G213="", "", IF(ISNUMBER(_xlfn.XMATCH(G213, 'State Google Tags on Account'!E:E)), "Found in Alicia API Pull", "MISSING in Alicia's API Pull")) -> Found in Alicia API Pull
A214: 295896210 | B214: 487657823 | C214: DPS - All Websites | D214: 346259813 | E214: DPS - DEM - Hazards | F214: https://hazards.utah.gov | G214: G-Z28SBKZ6MK | H214: =IF(G214="", "", IF(ISNUMBER(_xlfn.XMATCH(G214, 'Champions Sheet'!H:H)), "Found in Master", "MISSING in Alicia's")) -> MISSING in Alicia's | I214: =IF(G214="", "", IF(ISNUMBER(_xlfn.XMATCH(G214, 'State Google Tags on Account'!E:E)), "Found in Alicia API Pull", "MISSING in Alicia's API Pull")) -> Found in Alicia API Pull
A215: 295896210 | B215: 450964503 | C215: State of Utah Aggregate | D215: 346259813 | E215: DPS - DEM - Hazards | F215: https://hazards.utah.gov | G215: G-Z28SBKZ6MK | H215: =IF(G215="", "", IF(ISNUMBER(_xlfn.XMATCH(G215, 'Champions Sheet'!H:H)), "Found in Master", "MISSING in Alicia's")) -> MISSING in Alicia's | I215: =IF(G215="", "", IF(ISNUMBER(_xlfn.XMATCH(G215, 'State Google Tags on Account'!E:E)), "Found in Alicia API Pull", "MISSING in Alicia's API Pull")) -> Found in Alicia API Pull
... A383: 295896210 | B383: 450964503 | C383: State of Utah Aggregate | D383: 346607534 | E383: CCE - STEM Action Center | F383: https://stem.utah.gov | G383: G-E8MH5K8MC9 | H383: =IF(G383="", "", IF(ISNUMBER(_xlfn.XMATCH(G383, 'Champions Sheet'!H:H)), "Found in Master", "MISSING in Alicia's")) -> MISSING in Alicia's | I383: =IF(G383="", "", IF(ISNUMBER(_xlfn.XMATCH(G383, 'State Google Tags on Account'!E:E)), "Found in Alicia API Pull", "MISSING in Alicia's API Pull")) -> Found in Alicia API Pull
A384: 295896210 | B384: 482352716 | C384: DHHS - Roll-up - All properties | D384: 346723717 | E384: DHHS - IH - SUMH - sumh.utah.gov | F384: https://sumh.utah.gov, http://dsamh.utah.gov | G384: G-WYEPYF677M, G-6NZV3JCM8T | H384: =IF(G384="", "", IF(ISNUMBER(_xlfn.XMATCH(G384, 'Champions Sheet'!H:H)), "Found in Master", "MISSING in Alicia's")) -> MISSING in Alicia's | I384: Manually found only G-6NZV3JCM8T
A385: 295896210 | B385: 450964503 | C385: State of Utah Aggregate | D385: 346723717 | E385: DHHS - IH - SUMH - sumh.utah.gov | F385: https://sumh.utah.gov, http://dsamh.utah.gov | G385: G-WYEPYF677M, G-6NZV3JCM8T | H385: =IF(G385="", "", IF(ISNUMBER(_xlfn.XMATCH(G385, 'Champions Sheet'!H:H)), "Found in Master", "MISSING in Alicia's")) -> MISSING in Alicia's | I385: =IF(G385="", "", IF(ISNUMBER(_xlfn.XMATCH(G385, 'State Google Tags on Account'!E:E)), "Found in Alicia API Pull", "MISSING in Alicia's API Pull")) -> MISSING in Alicia's API Pull
A386: 295896210 | B386: 450964503 | C386: State of Utah Aggregate | D386: 292131495 | E386: USTC - Main Website | F386: https://tax.utah.gov | G386: G-GVVFH83WVC | H386: =IF(G386="", "", IF(ISNUMBER(_xlfn.XMATCH(G386, 'Champions Sheet'!H:H)), "Found in Master", "MISSING in Alicia's")) -> Found in Master | I386: =IF(G386="", "", IF(ISNUMBER(_xlfn.XMATCH(G386, 'State Google Tags on Account'!E:E)), "Found in Alicia API Pull", "MISSING in Alicia's API Pull")) -> Found in Alicia API Pull
A387: 295896210 | B387: 457684582 | C387: USTC - Main Website, Income, Property | D387: 292131495 | E387: USTC - Main Website | F387: https://tax.utah.gov | G387: G-GVVFH83WVC | H387: =IF(G387="", "", IF(ISNUMBER(_xlfn.XMATCH(G387, 'Champions Sheet'!H:H)), "Found in Master", "MISSING in Alicia's")) -> Found in Master | I387: =IF(G387="", "", IF(ISNUMBER(_xlfn.XMATCH(G387, 'State Google Tags on Account'!E:E)), "Found in Alicia API Pull", "MISSING in Alicia's API Pull")) -> Found in Alicia API Pull
A388: 295896210 | B388: 483012671 | C388: CCE - All Public Websites | D388: 350523403 | E388: CCE - Thriving | F388: https://thriving.utah.gov | G388: G-SSVHPE2V3N | H388: =IF(G388="", "", IF(ISNUMBER(_xlfn.XMATCH(G388, 'Champions Sheet'!H:H)), "Found in Master", "MISSING in Alicia's")) -> MISSING in Alicia's | I388: =IF(G388="", "", IF(ISNUMBER(_xlfn.XMATCH(G388, 'State Google Tags on Account'!E:E)), "Found in Alicia API Pull", "MISSING in Alicia's API Pull")) -> Found in Alicia API Pull
A389: 295896210 | B389: 488601532 | C389: State of Utah Aggregate - Low Traffic | D389: 350523403 | E389: CCE - Thriving | F389: https://thriving.utah.gov | G389: G-SSVHPE2V3N | H389: =IF(G389="", "", IF(ISNUMBER(_xlfn.XMATCH(G389, 'Champions Sheet'!H:H)), "Found in Master", "MISSING in Alicia's")) -> MISSING in Alicia's | I389: =IF(G389="", "", IF(ISNUMBER(_xlfn.XMATCH(G389, 'State Google Tags on Account'!E:E)), "Found in Alicia API Pull", "MISSING in Alicia's API Pull")) -> Found in Alicia API Pull
A390: 295896210 | B390: 450964503 | C390: State of Utah Aggregate | D390: 291228599 | E390: GOEO - UOT | F390: https://travel.utah.gov | G390: G-H382HLSCWL | H390: =IF(G390="", "", IF(ISNUMBER(_xlfn.XMATCH(G390, 'Champions Sheet'!H:H)), "Found in Master", "MISSING in Alicia's")) -> MISSING in Alicia's | I390: =IF(G390="", "", IF(ISNUMBER(_xlfn.XMATCH(G390, 'State Google Tags on Account'!E:E)), "Found in Alicia API Pull", "MISSING in Alicia's API Pull")) -> Found in Alicia API Pull
A391: 295896210 | B391: 450964503 | C391: State of Utah Aggregate | D391: 345269596 | E391: Treasurer - Main Website | F391: https://treasurer.utah.gov | G391: G-RDT945T7N9 | H391: =IF(G391="", "", IF(ISNUMBER(_xlfn.XMATCH(G391, 'Champions Sheet'!H:H)), "Found in Master", "MISSING in Alicia's")) -> MISSING in Alicia's | I391: =IF(G391="", "", IF(ISNUMBER(_xlfn.XMATCH(G391, 'State Google Tags on Account'!E:E)), "Found in Alicia API Pull", "MISSING in Alicia's API Pull")) -> Found in Alicia API Pull
A392: 295896210 | B392: 488601532 | C392: State of Utah Aggregate - Low Traffic | D392: 345264877 | E392: Utah Charter School Finance Authority | F392: https://ucsfa.utah.gov/ | G392: G-6MPFYHM4H6 | H392: =IF(G392="", "", IF(ISNUMBER(_xlfn.XMATCH(G392, 'Champions Sheet'!H:H)), "Found in Master", "MISSING in Alicia's")) -> MISSING in Alicia's | I392: =IF(G392="", "", IF(ISNUMBER(_xlfn.XMATCH(G392, 'State Google Tags on Account'!E:E)), "Found in Alicia API Pull", "MISSING in Alicia's API Pull")) -> Found in Alicia API Pull
A393: 295896210 | B393: 450964503 | C393: State of Utah Aggregate | D393: 285499201 | E393: UDOT - Public Input | F393: https://udotinput.utah.gov, https://udotinput.utah.gov/bccstudy | G393: G-SEPEV4BJYF, G-57PBP09PTH | H393: =IF(G393="", "", IF(ISNUMBER(_xlfn.XMATCH(G393, 'Champions Sheet'!H:H)), "Found in Master", "MISSING in Alicia's")) -> MISSING in Alicia's | I393: Manuually found (two different agencies)
A394: 295896210 | B394: 487084052 | C394: DOC - All Public Websites | D394: 255775667 | E394: DOC - DOPL - UPHP | F394: https://uphp.utah.gov/ | G394: G-RTV6KNP85X | H394: =IF(G394="", "", IF(ISNUMBER(_xlfn.XMATCH(G394, 'Champions Sheet'!H:H)), "Found in Master", "MISSING in Alicia's")) -> MISSING in Alicia's | I394: =IF(G394="", "", IF(ISNUMBER(_xlfn.XMATCH(G394, 'State Google Tags on Account'!E:E)), "Found in Alicia API Pull", "MISSING in Alicia's API Pull")) -> Found in Alicia API Pull
A395: 295896210 | B395: 450964503 | C395: State of Utah Aggregate | D395: 255775667 | E395: DOC - DOPL - UPHP | F395: https://uphp.utah.gov/ | G395: G-RTV6KNP85X | H395: =IF(G395="", "", IF(ISNUMBER(_xlfn.XMATCH(G395, 'Champions Sheet'!H:H)), "Found in Master", "MISSING in Alicia's")) -> MISSING in Alicia's | I395: =IF(G395="", "", IF(ISNUMBER(_xlfn.XMATCH(G395, 'State Google Tags on Account'!E:E)), "Found in Alicia API Pull", "MISSING in Alicia's API Pull")) -> Found in Alicia API Pull
A396: 295896210 | B396: 488601532 | C396: State of Utah Aggregate - Low Traffic | D396: 346384838 | E396: DAF - Rapid Response Team | F396: https://urrt.utah.gov | G396: G-9B2BJX00ML | H396: =IF(G396="", "", IF(ISNUMBER(_xlfn.XMATCH(G396, 'Champions Sheet'!H:H)), "Found in Master", "MISSING in Alicia's")) -> Found in Master | I396: =IF(G396="", "", IF(ISNUMBER(_xlfn.XMATCH(G396, 'State Google Tags on Account'!E:E)), "Found in Alicia API Pull", "MISSING in Alicia's API Pull")) -> Found in Alicia API Pull
A397: 295896210 | B397: 483012671 | C397: CCE - All Public Websites | D397: 346721069 | E397: CCE - UServeUtah | F397: https://userve.utah.gov/ | G397: G-1RT859T9HN | H397: =IF(G397="", "", IF(ISNUMBER(_xlfn.XMATCH(G397, 'Champions Sheet'!H:H)), "Found in Master", "MISSING in Alicia's")) -> Found in Master | I397: =IF(G397="", "", IF(ISNUMBER(_xlfn.XMATCH(G397, 'State Google Tags on Account'!E:E)), "Found in Alicia API Pull", "MISSING in Alicia's API Pull")) -> Found in Alicia API Pull
A398: 295896210 | B398: 450964503 | C398: State of Utah Aggregate | D398: 346721069 | E398: CCE - UServeUtah | F398: https://userve.utah.gov/ | G398: G-1RT859T9HN | H398: =IF(G398="", "", IF(ISNUMBER(_xlfn.XMATCH(G398, 'Champions Sheet'!H:H)), "Found in Master", "MISSING in Alicia's")) -> Found in Master | I398: =IF(G398="", "", IF(ISNUMBER(_xlfn.XMATCH(G398, 'State Google Tags on Account'!E:E)), "Found in Alicia API Pull", "MISSING in Alicia's API Pull")) -> Found in Alicia API Pull
A399: 295896210 | B399: 483012671 | C399: CCE - All Public Websites | D399: 324735019 | E399: CCE - SHPO | F399: https://ushpo.utah.gov | G399: G-5SDH2CY979 | H399: =IF(G399="", "", IF(ISNUMBER(_xlfn.XMATCH(G399, 'Champions Sheet'!H:H)), "Found in Master", "MISSING in Alicia's")) -> Found in Master | I399: =IF(G399="", "", IF(ISNUMBER(_xlfn.XMATCH(G399, 'State Google Tags on Account'!E:E)), "Found in Alicia API Pull", "MISSING in Alicia's API Pull")) -> Found in Alicia API Pull
A400: 295896210 | B400: 450964503 | C400: State of Utah Aggregate | D400: 324735019 | E400: CCE - SHPO | F400: https://ushpo.utah.gov | G400: G-5SDH2CY979 | H400: =IF(G400="", "", IF(ISNUMBER(_xlfn.XMATCH(G400, 'Champions Sheet'!H:H)), "Found in Master", "MISSING in Alicia's")) -> Found in Master | I400: =IF(G400="", "", IF(ISNUMBER(_xlfn.XMATCH(G400, 'State Google Tags on Account'!E:E)), "Found in Alicia API Pull", "MISSING in Alicia's API Pull")) -> Found in Alicia API Pull
A401: 295896210 | B401: 482352716 | C401: DHHS - Roll-up - All properties | D401: 358011256 | E401: DHHS - utahsafehaven.org | F401: https://utahsafehaven.org | G401: G-7NJLQGN5V3 | H401: =IF(G401="", "", IF(ISNUMBER(_xlfn.XMATCH(G401, 'Champions Sheet'!H:H)), "Found in Master", "MISSING in Alicia's")) -> MISSING in Alicia's | I401: =IF(G401="", "", IF(ISNUMBER(_xlfn.XMATCH(G401, 'State Google Tags on Account'!E:E)), "Found in Alicia API Pull", "MISSING in Alicia's API Pull")) -> Found in Alicia API Pull
A402: 295896210 | B402: 450964503 | C402: State of Utah Aggregate | D402: 358011256 | E402: DHHS - utahsafehaven.org | F402: https://utahsafehaven.org | G402: G-7NJLQGN5V3 | H402: =IF(G402="", "", IF(ISNUMBER(_xlfn.XMATCH(G402, 'Champions Sheet'!H:H)), "Found in Master", "MISSING in Alicia's")) -> MISSING in Alicia's | I402: =IF(G402="", "", IF(ISNUMBER(_xlfn.XMATCH(G402, 'State Google Tags on Account'!E:E)), "Found in Alicia API Pull", "MISSING in Alicia's API Pull")) -> Found in Alicia API Pull
A403: 295896210 | B403: 450964503 | C403: State of Utah Aggregate | D403: 419482352 | E403: CPB - Utah State Capitol | F403: https://utahstatecapitol.utah.gov | G403: G-0TCMJHG46L | H403: =IF(G403="", "", IF(ISNUMBER(_xlfn.XMATCH(G403, 'Champions Sheet'!H:H)), "Found in Master", "MISSING in Alicia's")) -> MISSING in Alicia's | I403: =IF(G403="", "", IF(ISNUMBER(_xlfn.XMATCH(G403, 'State Google Tags on Account'!E:E)), "Found in Alicia API Pull", "MISSING in Alicia's API Pull")) -> Found in Alicia API Pull
A404: 295896210 | B404: 483039742 | C404: DGO - All Websites | D404: 483367298 | E404: DGO - Vantage Employee | F404: https://vantage.employee.utah.gov | G404: G-F8Z8EHQ7CZ | H404: =IF(G404="", "", IF(ISNUMBER(_xlfn.XMATCH(G404, 'Champions Sheet'!H:H)), "Found in Master", "MISSING in Alicia's")) -> MISSING in Alicia's | I404: =IF(G404="", "", IF(ISNUMBER(_xlfn.XMATCH(G404, 'State Google Tags on Account'!E:E)), "Found in Alicia API Pull", "MISSING in Alicia's API Pull")) -> Found in Alicia API Pull
A405: 295896210 | B405: 450964503 | C405: State of Utah Aggregate | D405: 483367298 | E405: DGO - Vantage Employee | F405: https://vantage.employee.utah.gov | G405: G-F8Z8EHQ7CZ | H405: =IF(G405="", "", IF(ISNUMBER(_xlfn.XMATCH(G405, 'Champions Sheet'!H:H)), "Found in Master", "MISSING in Alicia's")) -> MISSING in Alicia's | I405: =IF(G405="", "", IF(ISNUMBER(_xlfn.XMATCH(G405, 'State Google Tags on Account'!E:E)), "Found in Alicia API Pull", "MISSING in Alicia's API Pull")) -> Found in Alicia API Pull
... A424: 295896210 | B424: 488601532 | C424: State of Utah Aggregate - Low Traffic | D424: 324315807 | E424: DOC - OPLR | F424: https://www.oplr.utah.gov | G424: G-RBM7685K7Q | H424: =IF(G424="", "", IF(ISNUMBER(_xlfn.XMATCH(G424, 'Champions Sheet'!H:H)), "Found in Master", "MISSING in Alicia's")) -> MISSING in Alicia's | I424: =IF(G424="", "", IF(ISNUMBER(_xlfn.XMATCH(G424, 'State Google Tags on Account'!E:E)), "Found in Alicia API Pull", "MISSING in Alicia's API Pull")) -> Found in Alicia API Pull
A425: 295896210 | B425: 482352716 | C425: DHHS - Roll-up - All properties | D425: 346707529 | E425: DHHS - Utah Developmental Disabilities Council - uddc.utah.gov | F425: https://www.utahddcouncil.org/, https://uddc.utah.gov | G425: G-T3WSYR5DTB, G-N0BP4CV2KP | H425: =IF(G425="", "", IF(ISNUMBER(_xlfn.XMATCH(G425, 'Champions Sheet'!H:H)), "Found in Master", "MISSING in Alicia's")) -> MISSING in Alicia's | I425: Manually found only G-T3WSYR5DTB
A426: 295896210 | B426: 488601532 | C426: State of Utah Aggregate - Low Traffic | D426: 346707529 | E426: DHHS - Utah Developmental Disabilities Council - uddc.utah.gov | F426: https://www.utahddcouncil.org/, https://uddc.utah.gov | G426: G-T3WSYR5DTB, G-N0BP4CV2KP | H426: =IF(G426="", "", IF(ISNUMBER(_xlfn.XMATCH(G426, 'Champions Sheet'!H:H)), "Found in Master", "MISSING in Alicia's")) -> MISSING in Alicia's | I426: Manually found only G-T3WSYR5DTB
A427: 295896210 | B427: 450964503 | C427: State of Utah Aggregate | D427: 360639014 | E427: LC - Main Website | F427: laborcommission.utah.gov/, https://laborcommission.at.utah.gov | G427: G-HF75VZKLLN, G-F4GMX1Q32E | H427: =IF(G427="", "", IF(ISNUMBER(_xlfn.XMATCH(G427, 'Champions Sheet'!H:H)), "Found in Master", "MISSING in Alicia's")) -> MISSING in Alicia's | I427: =IF(G427="", "", IF(ISNUMBER(_xlfn.XMATCH(G427, 'State Google Tags on Account'!E:E)), "Found in Alicia API Pull", "MISSING in Alicia's API Pull")) -> MISSING in Alicia's API Pull

Sheet Master Sheet
A1: Agency | B1: Original Data Collection | C1: Website_Title | D1: Host Name | E1: URL Path | F1: Status | G1: GTM | H1: G-Tag | I1: State of Utah GA Account Y/N | J1: GA property Name | K1: Missing?
A2: BOPP | B2: bop.utah.gov | C2: Board of Pardons & Parole | D2: bop.utah.gov | E2: https://bop.utah.gov | F2: Active (200) | G2: GTM-T34QF72M | H2: G-4VZFST59D0 | I2: Yes | J2: BOPP - Main Website | K2: Found in Rollup
A3: CCE | B3: pulled from google analytics | C3: N/A | D3: history.utah.gov | E3: https://history.utah.gov | F3: Active | G3: N/A | H3: G-TRQWCP98L2 | I3: Yes | J3: CCE - HS | K3: Taken from Rollup
A4: CCE | B4: https://artsandmuseums.utah.gov/ | C4: Utah Division of Arts & Museums | A Division of the Department of Cultural & Community Engagement | D4: artsandmuseums.utah.gov | E4: https://artsandmuseums.utah.gov/ | F4: Active (200) | G4: None Found | H4: G-76RDJXHW4B | I4: Yes | J4: CCE - AM | K4: Found in Rollup
A5: CCE | B5: pulled from google analytics | C5: N/A | D5: museumsocialimpact.org | E5: https://museumsocialimpact.org | F5: Active | G5: N/A | H5: G-4ERD645EY8 | I5: Yes | J5: CCE - AM - Museum Social Impact | K5: Taken from Rollup
A6: CCE | B6: pulled from google analytics | C6: N/A | D6: america250.utah.gov | E6: https://america250.utah.gov | F6: Active | G6: N/A | H6: G-104CMG7MZ8 | I6: Yes | J6: CCE - America 250 | K6: Taken from Rollup
A7: CCE | B7: pulled from google analytics | C7: N/A | D7: flag.utah.gov | E7: https://flag.utah.gov | F7: Active | G7: N/A | H7: G-TJYRDR531R | I7: Yes | J7: CCE - Flag | K7: Taken from Rollup
A8: CCE | B8: pulled from google analytics | C8: N/A | D8: historytogo.utah.gov | E8: https://historytogo.utah.gov | F8: Active | G8: N/A | H8: G-1Z3CWEGE6D | I8: Yes | J8: CCE - HS - History To Go | K8: Taken from Rollup
A9: CCE | B9: pulled from google analytics | C9: N/A | D9: ilovehistory.utah.gov | E9: https://ilovehistory.utah.gov | F9: Active | G9: N/A | H9: G-TMNJHE73N5 | I9: Yes | J9: CCE - HS - ILoveHistory | K9: Taken from Rollup
A10: CCE | B10: https://indian.utah.gov/ | C10: Utah Division of Indian Affairs | A Division of the Department of Cultural & Community Engagement | D10: indian.utah.gov | E10: https://indian.utah.gov/ | F10: Active (200) | G10: None Found | H10: G-L41CPHPD25 | I10: Yes | J10: CCE - IA | K10: Found in Rollup
A11: CCE | B11: pulled from google analytics | C11: N/A | D11: cceintranet.utah.gov | E11: https://cceintranet.utah.gov | F11: Active | G11: N/A | H11: G-6HVSGMMQCC | I11: Yes | J11: CCE - Intranet | K11: Taken from Rollup
A12: CCE | B12: https://multicultural.utah.gov/ | C12: Utah Division Of Multicultural Affairs | A Division of the Utah Department of Cultural and Community Engagement | D12: multicultural.utah.gov | E12: https://multicultural.utah.gov/ | F12: Active (200) | G12: None Found | H12: G-BGQYP4L42X | I12: Yes | J12: CCE - MA | K12: Found in Rollup
... A31: CCJJ | B31: https://justice.utah.gov/ | C31: Department of Criminal Justice | D31: justice.utah.gov | E31: https://justice.utah.gov/ | F31: Active (200) | G31: None Found | H31: G-9SLZ0P2YXT | I31: Yes | J31: CCJJ - Main Website | K31: Found in Rollup
A32: CCJJ | B32: https://justice.utah.gov/about-2/ | D32: justice.utah.gov | E32: https://justice.utah.gov/about-2/ | F32: Error (404) | G32: HTTP 404 | H32: G-9SLZ0P2YXT | I32: Yes | J32: CCJJ - Main Website | K32: Found in Rollup
A33: CCJJ | B33: https://justice.utah.gov/about-ccjj/extraditions/ | C33: Extraditions | Department of Criminal Justice | D33: justice.utah.gov | E33: https://justice.utah.gov/about-ccjj/extraditions/ | F33: Active (200) | G33: None Found | H33: G-9SLZ0P2YXT | I33: Yes | J33: CCJJ - Main Website | K33: Found in Rollup
A34: CCJJ | B34: https://justice.utah.gov/about-ccjj/judicial-nominating-commission/ | C34: Judicial Nominating Commission | Department of Criminal Justice | D34: justice.utah.gov | E34: https://justice.utah.gov/about-ccjj/judicial-nominating-commission/ | F34: Active (200) | G34: None Found | H34: G-9SLZ0P2YXT | I34: Yes | J34: CCJJ - Main Website | K34: Found in Rollup
A35: CCJJ | B35: https://justice.utah.gov/grants/ | C35: Grants | Department of Criminal Justice | D35: justice.utah.gov | E35: https://justice.utah.gov/grants/ | F35: Active (200) | G35: None Found | H35: G-9SLZ0P2YXT | I35: Yes | J35: CCJJ - Main Website | K35: Found in Rollup
A36: CCJJ | B36: https://justice.utah.gov/grants/federal-funding/ | C36: Federal Funding | Department of Criminal Justice | D36: justice.utah.gov | E36: https://justice.utah.gov/grants/federal-funding/ | F36: Active (200) | G36: None Found | H36: G-9SLZ0P2YXT | I36: Yes | J36: CCJJ - Main Website | K36: Found in Rollup
A37: CCJJ | B37: https://justice.utah.gov/grants/state-funding/ | C37: State Funding | Department of Criminal Justice | D37: justice.utah.gov | E37: https://justice.utah.gov/grants/state-funding/ | F37: Active (200) | G37: None Found | H37: G-9SLZ0P2YXT | I37: Yes | J37: CCJJ - Main Website | K37: Found in Rollup
A38: CCJJ | B38: https://justice.utah.gov/juvenile-justice/ | D38: justice.utah.gov | E38: https://justice.utah.gov/juvenile-justice/ | F38: Error (404) | G38: HTTP 404 | H38: G-9SLZ0P2YXT | I38: Yes | J38: CCJJ - Main Website | K38: Found in Rollup
A39: CCJJ | B39: https://justice.utah.gov/research-and-reports/ | D39: justice.utah.gov | E39: https://justice.utah.gov/research-and-reports/ | F39: Error (404) | G39: HTTP 404 | H39: G-9SLZ0P2YXT | I39: Yes | J39: CCJJ - Main Website | K39: Found in Rollup
A40: CCJJ | B40: https://justice.utah.gov/sentencing/ | D40: justice.utah.gov | E40: https://justice.utah.gov/sentencing/ | F40: Error (404) | G40: HTTP 404 | H40: G-9SLZ0P2YXT | I40: Yes | J40: CCJJ - Main Website | K40: Found in Rollup
A41: CCJJ | B41: https://justice.utah.gov/sentencing/eforms/ | C41: eForms | Department of Criminal Justice | D41: justice.utah.gov | E41: https://justice.utah.gov/sentencing/eforms/ | F41: Active (200) | G41: None Found | H41: G-9SLZ0P2YXT | I41: Yes | J41: CCJJ - Main Website | K41: Found in Rollup
A42: CCJJ | B42: https://justice.utah.gov/sentencing/sentencing-and-release-guidelines/ | D42: justice.utah.gov | E42: https://justice.utah.gov/sentencing/sentencing-and-release-guidelines/ | F42: Error (404) | G42: HTTP 404 | H42: G-9SLZ0P2YXT | I42: Yes | J42: CCJJ - Main Website | K42: Found in Rollup
A43: CCJJ | B43: https://crimevictim.utah.gov/grants/grant-solicitations/ | D43: crimevictim.utah.gov | E43: https://crimevictim.utah.gov/grants/grant-solicitations/ | F43: Error (404) | G43: HTTP 404 | H43: G-2NQRP84TH7 | I43: Yes | J43: CCJJ - UOVC | K43: Found in Rollup
A44: CCJJ | B44: https://crimevictim.utah.gov/victim-financial-assistance/application-process/ | D44: crimevictim.utah.gov | E44: https://crimevictim.utah.gov/victim-financial-assistance/application-process/ | F44: Error (404) | G44: HTTP 404 | H44: G-2NQRP84TH7 | I44: Yes | J44: CCJJ - UOVC | K44: Found in Rollup
A45: CCJJ | B45: https://crimevictim.utah.gov/victim-rights/ | D45: crimevictim.utah.gov | E45: https://crimevictim.utah.gov/victim-rights/ | F45: Error (404) | G45: HTTP 404 | H45: G-2NQRP84TH7 | I45: Yes | J45: CCJJ - UOVC | K45: Found in Rollup
A46: DABS | B46: parentsempowered.org | C46: Parents Empowered | D46: parentsempowered.org | E46: https://parentsempowered.org | F46: Active (200) | G46: GTM-53KZVQ | H46: G-3PPNCS7EKQ | I46: No | J46: Tag Firing but Not Found in State Analytics | K46: MISSING in Rollup
A47: CPB | B47: pulled from google analytics | C47: N/A | D47: utahstatecapitol.utah.gov | E47: https://utahstatecapitol.utah.gov | F47: Active | G47: N/A | H47: G-0TCMJHG46L | I47: Yes | J47: CPB - Utah State Capitol | K47: Taken from Rollup
A48: CSRO | B48: pulled from google analytics | C48: N/A | D48: csro.utah.gov | E48: https://csro.utah.gov | F48: Active | G48: N/A | H48: G-RWZKPNR2NS | I48: Yes | J48: CSRO - Career Service Review Office | K48: Taken from Rollup
A49: DABS | B49: abs.utah.gov | C49: Utah DABS - Utah DABS | D49: abs.utah.gov | E49: https://abs.utah.gov | F49: Active (200) | G49: GTM-5DQJR6SM | H49: G-X5QN659TK4 | I49: Yes | J49: DABS - Main Website | K49: Found in Rollup
A50: DABS | B50: Licensee Ordering Portal | C50: Licensee Ordering Portal | D50: abs.utah.gov | E50: https://abs.utah.gov/licenses-permits/licensee-orders/ | F50: No Original Link | G50: GTM-5DQJR6SM | H50: G-X5QN659TK4 | I50: Yes | J50: DABS - Main Website | K50: Found in Rollup
A51: DABS | B51: Licensing and Permitting System | C51: Licensing and Permitting System | D51: abs.utah.gov | E51: https://abs.utah.gov/licenses-permits/licensing-system/ | F51: No Original Link | G51: GTM-5DQJR6SM | H51: G-X5QN659TK4 | I51: Yes | J51: DABS - Main Website | K51: Found in Rollup
A52: DABS | B52: Learning Portal (SABA) | C52: Learning Portal (SABA) | D52: abs.utah.gov | E52: https://abs.utah.gov/licenses-permits/training/ | F52: No Original Link | G52: GTM-5DQJR6SM | H52: G-X5QN659TK4 | I52: Yes | J52: DABS - Main Website | K52: Found in Rollup
A53: DABS | B53: Special Ordering Portal | C53: Special Ordering Portal | D53: abs.utah.gov | E53: https://abs.utah.gov/shop-products/special-orders/ | F53: No Original Link | G53: GTM-5DQJR6SM | H53: G-X5QN659TK4 | I53: Yes | J53: DABS - Main Website | K53: Found in Rollup
A54: DABS | B54: Vendor Portal | C54: Vendor Portal | D54: abs.utah.gov | E54: https://abs.utah.gov/vendors/vendor-portal/ | F54: No Original Link | G54: GTM-5DQJR6SM | H54: G-X5QN659TK4 | I54: Yes | J54: DABS - Main Website | K54: Found in Rollup
A55: DABS | B55: Product Locator | C55: Product Locator | D55: webapps2.abc.utah.gov | E55: https://webapps2.abc.utah.gov/ProdApps/ProductLocatorCore | F55: No Original Link | G55: None Found | H55: G-X5QN659TK4 | I55: Yes | J55: DABS - Main Website | K55: Found in Rollup
A56: DABS | B56: Rare and High Demand Products Portal | C56: Rare and High Demand Products Portal | D56: webapps2.abc.utah.gov | E56: https://webapps2.abc.utah.gov/ProdApps/RareHighDemandProducts | F56: No Original Link | G56: None Found | H56: G-X5QN659TK4 | I56: Yes | J56: DABS - Main Website | K56: Found in Rollup
A57: DPS | B57: https://publicsafetyutah.govqa.us/WEBAPP/_rs/(S(zfixk5ebkudzdn0wyzgrv2jk))/SupportHome.aspx?&lp=9 | C57: Utah Department of Public Safety | Records Center | D57: publicsafetyutah.govqa.us | E57: https://publicsafetyutah.govqa.us/WEBAPP/_rs/(S(zfixk5ebkudzdn0wyzgrv2jk))/SupportHome.aspx?&lp=9 | F57: Active (200) | G57: None Found | H57: G-4SLB68RYEV, UA-113043676-70 | I57: No | J57: Tag Firing but Not Found in State Analytics | K57: MISSING in Rollup
... A133: DWS | B133: jobs.utah.gov/jobseeker | C133: Job Seekers | D133: jobs.utah.gov | E133: https://jobs.utah.gov/jobseeker | F133: Active (200) | G133: GTM-PL8ZV9W | H133: G-DYDNPQ9XL9 | I133: No | J133: Tag Firing but Not Found in State Analytics | K133: MISSING in Rollup
A134: DWS | B134: jobs.utah.gov/mycase | D134: jobs.utah.gov | E134: https://jobs.utah.gov/mycase | F134: Error (404) | G134: HTTP 404 | H134: G-DYDNPQ9XL9 | I134: No | J134: Tag Firing but Not Found in State Analytics | K134: MISSING in Rollup
A135: DWS | B135: jobs.utah.gov/refugee | C135: Refugee Services | D135: jobs.utah.gov | E135: https://jobs.utah.gov/refugee | F135: Active (200) | G135: None Found | H135: G-DYDNPQ9XL9 | I135: No | J135: Tag Firing but Not Found in State Analytics | K135: MISSING in Rollup
A136: DWS | B136: jobs.utah.gov/ui | C136: Unemployment Insurance | D136: jobs.utah.gov | E136: https://jobs.utah.gov/ui | F136: Active (200) | G136: None Found | H136: G-DYDNPQ9XL9 | I136: No | J136: Tag Firing but Not Found in State Analytics | K136: MISSING in Rollup
A137: DWS | B137: jobs.utah.gov/usor | C137: Utah State Office of Rehabilitation | D137: jobs.utah.gov | E137: https://jobs.utah.gov/usor | F137: Active (200) | G137: None Found | H137: G-DYDNPQ9XL9 | I137: No | J137: Tag Firing but Not Found in State Analytics | K137: MISSING in Rollup
A138: DWS | B138: jobs.utah.gov/wi | C138: Economic Data Landing Page | D138: jobs.utah.gov | E138: https://jobs.utah.gov/wi | F138: Active (200) | G138: None Found | H138: G-DYDNPQ9XL9 | I138: No | J138: Tag Firing but Not Found in State Analytics | K138: MISSING in Rollup
A139: DNR | B139: https://www.utahmapstore.com | C139: Natural Resources Map & Bookstore – The Natural Resources Map & Bookstore | D139: utahmapstore.com | E139: https://www.utahmapstore.com | F139: Active (200) | G139: GTM-NF7LL2Q | H139: G-E340LM0429 | I139: No | J139: Tag Firing but Not Found in State Analytics | K139: MISSING in Rollup
A140: UDOT | B140: cottonwoodcanyons.udot.utah.gov | C140: Home - Cottonwood Canyons - Roads to Recreation | D140: cottonwoodcanyons.udot.utah.gov | E140: https://cottonwoodcanyons.udot.utah.gov | F140: Active (200) | G140: None Found | H140: G-E7DE196ZDT | I140: No | J140: Tag Firing but Not Found in State Analytics | K140: MISSING in Rollup
A141: DOC | B141: https://secure.utah.gov/ce-provider | C141: Log in with Your Utah.gov Account | Account Management | Utah.gov | D141: https://secure.utah.gov/ce-provider | E141: https://secure.utah.gov/ce-provider | F141: Active (200) | G141: GTM-MRN3MSX | H141: G-ELDEEFYB93, G-NQPSEQJFS6, G-PRL0QTE0VR, UA-103830962-19, UA-15325774-11 | I141: No | J141: Tag Firing but Not Found in State Analytics | K141: MISSING in Rollup
A142: DPS | B142: https://secure.utah.gov/account/login.html | C142: Log in with Your Utah.gov Account | Account Management | Utah.gov | D142: https://secure.utah.gov/account/login.html | E142: https://secure.utah.gov/account/login.html | F142: Active (200) | G142: GTM-MRN3MSX | H142: G-ELDEEFYB93, G-NQPSEQJFS6, G-PRL0QTE0VR, UA-103830962-19, UA-15325774-11 | I142: No | J142: Tag Firing but Not Found in State Analytics | K142: MISSING in Rollup
A143: DOC | B143: https://secure.utah.gov/doplrenewal | D143: https://secure.utah.gov/doplrenewal | E143: https://secure.utah.gov/doplrenewal | F143: Error (404) | G143: GTM-MRN3MSX | H143: G-ELDEEFYB93, G-VKFVYQLH65, UA-103830962-9, UA-827740-13 | I143: No | J143: Tag Firing but Not Found in State Analytics | K143: MISSING in Rollup
A144: DHHS | B144: pulled from google analytics | C144: N/A | D144: coronavirus.utah.gov | E144: https://coronavirus.utah.gov | F144: Active | G144: N/A | H144: G-6P4NJPBHCY | I144: Yes | J144: DHHS - [RETIRED] coronavirus.utah.gov | K144: Taken from Rollup
A145: DHHS | B145: daas.utah.gov | C145: Aging & Adult Services – Utah DHHS | Services for Utah's Aging Adults | D145: daas.utah.gov | E145: https://daas.utah.gov | F145: Active (200) | G145: GTM-P334MTZ9 | H145: G-N8LE1HBTT1 | I145: Yes | J145: DHHS - DAAS - daas.utah.gov | K145: Found in Rollup
A146: DHHS | B146: pulled from google analytics | C146: N/A | D146: dementia.utah.gov | E146: https://dementia.utah.gov | F146: Active | G146: N/A | H146: G-27FQZQKJDB | I146: Yes | J146: DHHS - DAAS - dementia.utah.gov | K146: Taken from Rollup
A147: DHHS | B147: pulled from google analytics | C147: N/A | D147: leaps.dhhs.utah.gov | E147: https://leaps.dhhs.utah.gov | F147: Active | G147: N/A | H147: G-DMEN06W0CY | I147: Yes | J147: DHHS - DAAS - leaps.dhhs.utah.gov | K147: Taken from Rollup
A148: DHHS | B148: dcfs.utah.gov | C148: Child and Family Services – Utah DHHS | Strengthening families. Protecting children. | D148: dcfs.utah.gov | E148: https://dcfs.utah.gov | F148: Active (200) | G148: GTM-N6825ZM7 | H148: G-WBTLVBKJKV | I148: Yes | J148: DHHS - DCFS - dcfs.utah.gov | K148: Found in Rollup
A149: DHHS | B149: pulled from google analytics | C149: N/A | D149: adolescenthealth.utah.gov | E149: https://adolescenthealth.utah.gov | F149: Active | G149: N/A | H149: G-8B11ZKP6V6 | I149: Yes | J149: DHHS - DFH - adolescenthealth.utah.gov | K149: Taken from Rollup
A150: DHHS | B150: pulled from google analytics | C150: N/A | D150: earlychildhood.utah.gov | E150: https://earlychildhood.utah.gov | F150: Active | G150: N/A | H150: G-8D5R689ZX2 | I150: Yes | J150: DHHS - DFH - Early Childhood - earlychildhood.utah.gov | K150: Taken from Rollup
A151: DHHS | B151: familyhealth.utah.gov | C151: Division of Family Health – Utah DHHS | D151: familyhealth.utah.gov | E151: https://familyhealth.utah.gov | F151: Active (200) | G151: GTM-P48S3973 | H151: G-E9MV39ZQB9 | I151: Yes | J151: DHHS - DFH - familyhealth.utah.gov | K151: Found in Rollup
A152: DHHS | B152: pulled from google analytics | C152: N/A | D152: informedconsent.utah.gov | E152: https://informedconsent.utah.gov | F152: Active | G152: N/A | H152: G-GXG57N7WCJ | I152: Yes | J152: DHHS - DFH - informedconsent.utah.gov | K152: Taken from Rollup
A153: DHHS | B153: pulled from google analytics | C153: N/A | D153: maternalmentalhealth.utah.gov | E153: https://maternalmentalhealth.utah.gov | F153: Active | G153: N/A | H153: G-5M0X7QNVE1 | I153: Yes | J153: DHHS - DFH - maternalmentalhealth.dhhs.utah.gov | K153: Taken from Rollup
A154: DHHS | B154: mihp.utah.gov | C154: Maternal and Infant Health Program | Utah Department of Health and Human Services | D154: mihp.utah.gov | E154: https://mihp.utah.gov | F154: Active (200) | G154: GTM-WHHK8Z5N | H154: G-2TKZEJVEDJ | I154: Yes | J154: DHHS - DFH - mihp.utah.gov | K154: Found in Rollup
A155: DHHS | B155: pulled from google analytics | C155: N/A | D155: dlbc.utah.gov | E155: http://dlbc.utah.gov | F155: Active | G155: N/A | H155: G-Z8E586EN9V | I155: Yes | J155: DHHS - DLBC - dlbc.utah.gov | K155: Taken from Rollup
... A252: CCE | B252: https://history.utah.gov/ | C252: Utah Historical Society | The Utah Historical Society is a division of the Utah Department of Cultural & Community Engagement | D252: history.utah.gov | E252: https://history.utah.gov/ | F252: Active (200) | G252: HTTP 403 | H252: None Found | I252: No | J252: No Live Tag Firing | K252: MISSING in Rollup
A253: CCJJ | B253: https://idc.utah.gov/grants/grant-application | D253: idc.utah.gov | E253: https://idc.utah.gov/grants/grant-application | F253: Error (404) | G253: HTTP 404 | H253: None Found | I253: No | J253: No Live Tag Firing | K253: MISSING in Rollup
A254: DABS | B254: Product Locator App | C254: Product Locator App | D254: apps.apple.com | E254: https://apps.apple.com/us/app/ut-dabs-app/id1471992994 | F254: No Original Link | G254: None Found | H254: None Found | I254: No | J254: No Live Tag Firing | K254: MISSING in Rollup
A255: DEQ | B255: air.utah.gov | C255: Utah DEQ: DAQ: Current Conditions: Salt Lake County | D255: air.utah.gov | E255: https://air.utah.gov | F255: Active (200) | G255: None Found | H255: None Found | I255: No | J255: No Live Tag Firing | K255: MISSING in Rollup
A256: DEQ | B256: MBE/WBE Procurement Report | C256: MBE/WBE Procurement Report | D256: lf-public.deq.utah.gov | E256: https://lf-public.deq.utah.gov/WebLink/DocView.aspx?id=632748&dbid=0&repo=Public | F256: No Original Link | G256: None Found | H256: None Found | I256: No | J256: No Live Tag Firing | K256: MISSING in Rollup
A257: DEQ | B257: lf-public.deq.utah.gov/WebLink/Welcome.aspx | C257: Utah Department of Environmental Quality EQDocs | D257: lf-public.deq.utah.gov | E257: https://lf-public.deq.utah.gov/WebLink/Welcome.aspx | F257: Active (200) | G257: None Found | H257: None Found | I257: No | J257: No Live Tag Firing | K257: MISSING in Rollup
A258: DEQ | B258: waterlink.utah.gov/ | C258: Waterlink | D258: waterlink.utah.gov | E258: https://waterlink.utah.gov | F258: Active (200) | G258: None Found | H258: None Found | I258: No | J258: No Live Tag Firing | K258: MISSING in Rollup
A259: DGO | B259: SAP Concur (URL: https://www.concursolutions.com/) | D259: concursolutions.com | E259: https://www.concursolutions.com/) | F259: Error (404) | G259: HTTP 404 | H259: None Found | I259: No | J259: No Live Tag Firing | K259: MISSING in Rollup
A260: DGO | B260: employee.utah.gov | C260: UtahID | D260: employee.utah.gov | E260: https://employee.utah.gov | F260: Active (200) | G260: None Found | H260: None Found | I260: No | J260: No Live Tag Firing | K260: MISSING in Rollup
A261: DGO | B261: Finance Support Submit a ticket (https://financesupport.utah.gov/portal/en/newticket) | D261: financesupport.utah.gov | E261: https://financesupport.utah.gov/portal/en/newticket) | F261: Error (404) | G261: HTTP 404 | H261: None Found | I261: No | J261: No Live Tag Firing | K261: MISSING in Rollup
A262: DGO | B262: gateway.utah.gov | C262: UtahID | D262: gateway.utah.gov | E262: https://gateway.utah.gov | F262: Active (200) | G262: None Found | H262: None Found | I262: No | J262: No Live Tag Firing | K262: MISSING in Rollup
A263: DOC | B263: pulled from google analytics | C263: N/A | D263: admin.commerce.utah.gov | E263: https://admin.commerce.utah.gov | F263: Active | G263: N/A | H263: G-XTZ95C217Z | I263: Yes | J263: DOC - Administration | K263: Taken from Rollup
A264: DOC | B264: pulled from google analytics | C264: N/A | D264: commerce.utah.gov | E264: http://commerce.utah.gov | F264: Active | G264: N/A | H264: G-PZZ62EM49P | I264: Yes | J264: DOC - All Websites - commerce.utah.gov | K264: Taken from Rollup
A265: DOC | B265: pulled from google analytics | C265: N/A | D265: blog.commerce.utah.gov | E265: https://blog.commerce.utah.gov | F265: Active | G265: N/A | H265: G-E6HM2EH098 | I265: Yes | J265: DOC - Blog | K265: Taken from Rollup
A266: DOC | B266: pulled from google analytics | C266: N/A | D266: corporations.utah.gov | E266: http://corporations.utah.gov | F266: Active | G266: N/A | H266: G-RED8SLHVQ3 | I266: Yes | J266: DOC - CORP | K266: Taken from Rollup
A267: DOC | B267: pulled from google analytics | C267: N/A | D267: db.corporations.gov | E267: https://db.corporations.gov/gia/ | F267: Active | G267: N/A | H267: G-4HVDLQN6RG | I267: Yes | J267: DOC - CORP - GIA Database | K267: Taken from Rollup
A268: DOC | B268: pulled from google analytics | C268: N/A | D268: db.corporations.utah.gov | E268: https://db.corporations.utah.gov/moraa/ | F268: Active | G268: N/A | H268: G-WE9DYFJK64 | I268: Yes | J268: DOC - CORP - MoRAA | K268: Taken from Rollup
A269: DOC | B269: pulled from google analytics | C269: N/A | D269: secure.utah.gov | E269: https://secure.utah.gov/trademark/ | F269: Active | G269: N/A | H269: G-YM2B0RK169 | I269: Yes | J269: DOC - CORP - Trademark Manager | K269: Taken from Rollup
A270: DOC | B270: pulled from google analytics | C270: N/A | D270: dcp.utah.gov | E270: https://dcp.utah.gov | F270: Active | G270: N/A | H270: G-2N57PZERBL | I270: Yes | J270: DOC - DCP | K270: Taken from Rollup
A271: DOC | B271: pulled from google analytics | C271: N/A | D271: socialmedia.utah.gov | E271: https://socialmedia.utah.gov | F271: Active | G271: N/A | H271: G-F6M4TZGBHX | I271: Yes | J271: DOC - DCP - Social Media | K271: Taken from Rollup
A272: DOC | B272: pulled from google analytics | C272: N/A | D272: dcp.utah.gov | E272: http://dcp.utah.gov/ | F272: Active | G272: N/A | H272: G-CVR3K81XQZ | I272: Yes | J272: DOC - DCP, OCS, DRE | K272: Taken from Rollup
A273: DOC | B273: pulled from google analytics | C273: N/A | D273: dopl.utah.gov | E273: http://dopl.utah.gov | F273: Active | G273: N/A | H273: G-62Q1EJNC45 | I273: Yes | J273: DOC - DOPL | K273: Taken from Rollup
... A300: DNR | B300: recreation.utah.gov | C300: Division of Outdoor Recreation | D300: recreation.utah.gov | E300: https://recreation.utah.gov | F300: Active (200) | G300: HTTP 403 | H300: None Found | I300: No | J300: No Live Tag Firing | K300: MISSING in Rollup
A301: DNR | B301: https://www.utah-hunt.com/ | D301: utah-hunt.com | E301: https://www.utah-hunt.com/ | F301: Error (404) | G301: HTTP 404 | H301: None Found | I301: No | J301: No Live Tag Firing | K301: MISSING in Rollup
A302: DNR | B302: https://www.waterrights.utah.gov | C302: Utah Water Rights | D302: waterrights.utah.gov | E302: https://www.waterrights.utah.gov | F302: Active (200) | G302: None Found | H302: None Found | I302: No | J302: No Live Tag Firing | K302: MISSING in Rollup
A303: DOC | B303: https://admin.commerce.utah.gov | C303: Utah Department of Commerce | D303: admin.commerce.utah.gov | E303: https://admin.commerce.utah.gov | F303: Active (200) | G303: HTTP 403 | H303: None Found | I303: No | J303: No Live Tag Firing | K303: MISSING in Rollup
A304: DOC | B304: https://blog.commerce.utah.gov | C304: Could not fetch title | D304: blog.commerce.utah.gov | E304: https://blog.commerce.utah.gov | F304: Active (200) | G304: HTTP 403 | H304: None Found | I304: No | J304: No Live Tag Firing | K304: MISSING in Rollup
A305: DOC | B305: https://businessregistration.utah.gov/ | C305: Utah Business Registration | D305: businessregistration.utah.gov | E305: https://businessregistration.utah.gov/ | F305: Active (200) | G305: None Found | H305: None Found | I305: No | J305: No Live Tag Firing | K305: MISSING in Rollup
A306: DOC | B306: https://busu.sgut.civixapps.com/ | C306: Utah Business Registration | D306: busu.sgut.civixapps.com | E306: https://busu.sgut.civixapps.com/ | F306: Active (200) | G306: None Found | H306: None Found | I306: No | J306: No Live Tag Firing | K306: MISSING in Rollup
A307: DOC | B307: https://commerce.utah.gov | C307: Could not fetch title | D307: commerce.utah.gov | E307: https://commerce.utah.gov | F307: Active (200) | G307: HTTP 403 | H307: None Found | I307: No | J307: No Live Tag Firing | K307: MISSING in Rollup
A308: DOC | B308: https://www.commerce.utah.gov | C308: Could not fetch title | D308: commerce.utah.gov | E308: https://www.commerce.utah.gov | F308: Active (200) | G308: HTTP 403 | H308: None Found | I308: No | J308: No Live Tag Firing | K308: MISSING in Rollup
A309: DOC | B309: https://corporations.utah.gov | C309: Division of Corporations & Commercial Code | D309: corporations.utah.gov | E309: https://corporations.utah.gov | F309: Active (200) | G309: HTTP 403 | H309: None Found | I309: No | J309: No Live Tag Firing | K309: MISSING in Rollup
A310: DOC | B310: https://dcp.utah.gov | C310: Division of Consumer Protection | D310: dcp.utah.gov | E310: https://dcp.utah.gov | F310: Active (200) | G310: HTTP 403 | H310: None Found | I310: No | J310: No Live Tag Firing | K310: MISSING in Rollup
A311: DOC | B311: https://dopl.utah.gov - | C311: Could not fetch title | D311: dopl.utah.gov | E311: https://dopl.utah.gov | F311: Active (200) | G311: HTTP 403 | H311: None Found | I311: No | J311: No Live Tag Firing | K311: MISSING in Rollup
A312: DOC | B312: https://dpu.utah.gov | C312: Division of Public Utilities | D312: dpu.utah.gov | E312: https://dpu.utah.gov | F312: Active (200) | G312: HTTP 403 | H312: None Found | I312: No | J312: No Live Tag Firing | K312: MISSING in Rollup
A313: DOC | B313: https://ocs.utah.gov | C313: Office of Consumer Services | D313: ocs.utah.gov | E313: https://ocs.utah.gov | F313: Active (200) | G313: HTTP 403 | H313: None Found | I313: No | J313: No Live Tag Firing | K313: MISSING in Rollup
... A317: DOC | B317: https://secure.utah.gov/bes | C317: Utah Business Registration | D317: https://secure.utah.gov/bes | E317: https://secure.utah.gov/bes | F317: Active (200) | G317: None Found | H317: None Found | I317: No | J317: No Live Tag Firing | K317: MISSING in Rollup
A318: DOC | B318: https://secure.utah.gov/charities | D318: https://secure.utah.gov/charities | E318: https://secure.utah.gov/charities | F318: Error (404) | G318: HTTP 404 | H318: None Found | I318: No | J318: No Live Tag Firing | K318: MISSING in Rollup
...
